{
    "pageNumber": 159,
    "data": [
        {
            "id": "6286075",
            "title": "Ice Cream Maker Attachment | KitchenAid",
            "date_created": "1438302103",
            "loginId": "1758166",
            "tags": "",
            "description": "Attaches to your Stand Mixer to easily create up to 2 quarts of ice cream, sorbet, gelato and other frozen treats.",
            "asset": {
                "type": "youtube",
                "author": "KitchenAid",
                "hdvFlag": 0,
                "hookText": "Attaches to your Stand Mixer to easily create up to 2 quarts of ice cream, sorbet, gelato and other frozen treats.\n\nGo to http:\/\/www.kitchenaid.com\/countertop-appliances\/ for more countertop appliance information and culinary inspiration.",
                "tags": "",
                "thumbnailUrl": "https:\/\/i.ytimg.com\/vi\/1XoVpJXNEaI\/hqdefault.jpg",
                "videoId": "1XoVpJXNEaI",
                "mediaDuration": "46",
                "prettyDuration": "00:00:46"
            },
            "parentId": "114661406",
            "url": "\/latest-videos\/ice-cream-maker-attachment-kitchenaid\/114661406-6286075"
        },
        {
            "id": "115347414",
            "title": "ED Ellen DeGeneres Baby Collection",
            "date_created": "1504305015",
            "loginId": "1758166",
            "tags": "",
            "description": "",
            "asset": {
                "user": {
                    "firstName": "",
                    "lastName": "",
                    "emailAddress": ""
                },
                "videoMeta": {
                    "duration": "30",
                    "width": 1920,
                    "height": 1080
                },
                "mediaDuration": "30",
                "prettyDuration": "00:00:30",
                "thumbnailUrl": "\/\/v.tvpage.com\/1758166\/115347414\/47ee8\/thumb-39fc13e4f199f3da3c94a0ee75de6c8e-00001.jpg",
                "type": "mp4",
                "dashUrl": "\/\/v.tvpage.com\/1758166\/115347414\/47ee8\/media.mpd",
                "hlsUrl": "\/\/v.tvpage.com\/1758166\/115347414\/47ee8\/media.m3u8",
                "uploadAsset": false,
                "quality": "",
                "cc": [
                    {
                        "label": "English",
                        "srclang": "en",
                        "src": "\/\/v.tvpage.com\/1758166\/115347414\/cc\/vtt\/en_1516731506.vtt",
                        "default": true
                    }
                ],
                "sources": [
                    {
                        "file": "\/\/v.tvpage.com\/1758166\/115347414\/47ee8\/1080p_media.mp4",
                        "quality": "1080p",
                        "mime": "video\/mp4",
                        "width": 1920,
                        "height": 1080
                    },
                    {
                        "file": "\/\/v.tvpage.com\/1758166\/115347414\/47ee8\/720p_media.mp4",
                        "quality": "720p",
                        "mime": "video\/mp4",
                        "width": 1280,
                        "height": 720
                    },
                    {
                        "file": "\/\/v.tvpage.com\/1758166\/115347414\/47ee8\/480p_media.mp4",
                        "quality": "480p",
                        "mime": "video\/mp4",
                        "width": 854,
                        "height": 480
                    },
                    {
                        "file": "\/\/v.tvpage.com\/1758166\/115347414\/47ee8\/360p_media.mp4",
                        "quality": "360p",
                        "mime": "video\/mp4",
                        "width": 640,
                        "height": 360
                    },
                    {
                        "file": "\/\/v.tvpage.com\/1758166\/115347414\/47ee8\/240p_media.mp4",
                        "quality": "240p",
                        "mime": "video\/mp4",
                        "width": 320,
                        "height": 180
                    }
                ]
            },
            "parentId": "114661406",
            "url": "\/latest-videos\/ed-ellen-degeneres-baby-collection-mp4\/114661406-115347414"
        },
        {
            "id": "111180325",
            "title": "Cuisinart Coffee On Demand 12-Cup Programmable Coffee Maker",
            "date_created": "1502924425",
            "loginId": "1758166",
            "tags": "",
            "description": "",
            "asset": {
                "user": "",
                "videoMeta": {
                    "duration": "30",
                    "width": 960,
                    "height": 540
                },
                "mediaDuration": "30",
                "prettyDuration": "00:00:30",
                "thumbnailUrl": "\/\/sitecdn.tvpage.com\/live\/users\/1758166\/canvas\/1276\/709\/993643387-021276711.jpg",
                "type": "mp4",
                "dashUrl": "\/\/v.tvpage.com\/1758166\/111180325\/0ce4b\/media.mpd",
                "hlsUrl": "\/\/v.tvpage.com\/1758166\/111180325\/0ce4b\/media.m3u8",
                "cc": [
                    {
                        "label": "English",
                        "srclang": "en",
                        "src": "\/\/v.tvpage.com\/1758166\/111180325\/cc\/vtt\/en_1504119334.vtt",
                        "default": true
                    }
                ],
                "uploadAsset": false,
                "quality": "",
                "sources": [
                    {
                        "file": "\/\/v.tvpage.com\/1758166\/111180325\/0ce4b\/1080p_media.mp4",
                        "quality": "1080p",
                        "mime": "video\/mp4",
                        "width": 960,
                        "height": 540
                    },
                    {
                        "file": "\/\/v.tvpage.com\/1758166\/111180325\/0ce4b\/720p_media.mp4",
                        "quality": "720p",
                        "mime": "video\/mp4",
                        "width": 960,
                        "height": 540
                    },
                    {
                        "file": "\/\/v.tvpage.com\/1758166\/111180325\/0ce4b\/480p_media.mp4",
                        "quality": "480p",
                        "mime": "video\/mp4",
                        "width": 854,
                        "height": 480
                    },
                    {
                        "file": "\/\/v.tvpage.com\/1758166\/111180325\/0ce4b\/360p_media.mp4",
                        "quality": "360p",
                        "mime": "video\/mp4",
                        "width": 640,
                        "height": 360
                    },
                    {
                        "file": "\/\/v.tvpage.com\/1758166\/111180325\/0ce4b\/240p_media.mp4",
                        "quality": "240p",
                        "mime": "video\/mp4",
                        "width": 320,
                        "height": 180
                    }
                ]
            },
            "parentId": "114661406",
            "url": "\/latest-videos\/cuisinart-coffee-on-demand-12-cup-programmable-coffee-maker\/114661406-111180325"
        },
        {
            "id": "115258703",
            "title": "Cotton Origin",
            "date_created": "1504152463",
            "loginId": "1758166",
            "tags": "",
            "description": "",
            "asset": {
                "user": {
                    "firstName": "",
                    "lastName": "",
                    "emailAddress": ""
                },
                "videoMeta": {
                    "duration": "60",
                    "width": 1280,
                    "height": 720
                },
                "mediaDuration": "60",
                "prettyDuration": "00:01:00",
                "thumbnailUrl": "\/\/v.tvpage.com\/1758166\/115258703\/973e1\/thumb-42006a134f8ac26979599ac9ea83e45b-00001.jpg",
                "type": "mp4",
                "dashUrl": "\/\/v.tvpage.com\/1758166\/115258703\/973e1\/media.mpd",
                "hlsUrl": "\/\/v.tvpage.com\/1758166\/115258703\/973e1\/media.m3u8",
                "uploadAsset": false,
                "quality": "",
                "sources": [
                    {
                        "file": "\/\/v.tvpage.com\/1758166\/115258703\/973e1\/1080p_media.mp4",
                        "quality": "1080p",
                        "mime": "video\/mp4",
                        "width": 1280,
                        "height": 720
                    },
                    {
                        "file": "\/\/v.tvpage.com\/1758166\/115258703\/973e1\/720p_media.mp4",
                        "quality": "720p",
                        "mime": "video\/mp4",
                        "width": 1280,
                        "height": 720
                    },
                    {
                        "file": "\/\/v.tvpage.com\/1758166\/115258703\/973e1\/480p_media.mp4",
                        "quality": "480p",
                        "mime": "video\/mp4",
                        "width": 854,
                        "height": 480
                    },
                    {
                        "file": "\/\/v.tvpage.com\/1758166\/115258703\/973e1\/360p_media.mp4",
                        "quality": "360p",
                        "mime": "video\/mp4",
                        "width": 640,
                        "height": 360
                    },
                    {
                        "file": "\/\/v.tvpage.com\/1758166\/115258703\/973e1\/240p_media.mp4",
                        "quality": "240p",
                        "mime": "video\/mp4",
                        "width": 320,
                        "height": 180
                    }
                ],
                "cc": [
                    {
                        "label": "English",
                        "srclang": "en",
                        "src": "\/\/v.tvpage.com\/1758166\/115258703\/cc\/vtt\/en_1504153407.vtt",
                        "default": true
                    }
                ]
            },
            "parentId": "114661406",
            "url": "\/latest-videos\/media-2-mp4\/114661406-115258703"
        },
        {
            "id": "109984974",
            "title": "Shark Tank Simply Fit Board&reg;",
            "date_created": "1502521761",
            "loginId": "1758166",
            "tags": "",
            "description": "",
            "asset": {
                "user": "",
                "videoMeta": {
                    "duration": "83",
                    "width": 1280,
                    "height": 720
                },
                "mediaDuration": "83",
                "prettyDuration": "00:01:23",
                "thumbnailUrl": "\/\/v.tvpage.com\/1758166\/109984974\/d7c7c\/thumb-7c31d785e925e0588c22086a60a2917a-00002.jpg",
                "type": "mp4",
                "dashUrl": "\/\/v.tvpage.com\/1758166\/109984974\/d7c7c\/media.mpd",
                "hlsUrl": "\/\/v.tvpage.com\/1758166\/109984974\/d7c7c\/media.m3u8",
                "uploadAsset": false,
                "quality": "",
                "sources": [
                    {
                        "file": "\/\/v.tvpage.com\/1758166\/109984974\/d7c7c\/1080p_media.mp4",
                        "quality": "1080p",
                        "mime": "video\/mp4",
                        "width": 1280,
                        "height": 720
                    },
                    {
                        "file": "\/\/v.tvpage.com\/1758166\/109984974\/d7c7c\/720p_media.mp4",
                        "quality": "720p",
                        "mime": "video\/mp4",
                        "width": 1280,
                        "height": 720
                    },
                    {
                        "file": "\/\/v.tvpage.com\/1758166\/109984974\/d7c7c\/480p_media.mp4",
                        "quality": "480p",
                        "mime": "video\/mp4",
                        "width": 854,
                        "height": 480
                    },
                    {
                        "file": "\/\/v.tvpage.com\/1758166\/109984974\/d7c7c\/360p_media.mp4",
                        "quality": "360p",
                        "mime": "video\/mp4",
                        "width": 640,
                        "height": 360
                    },
                    {
                        "file": "\/\/v.tvpage.com\/1758166\/109984974\/d7c7c\/240p_media.mp4",
                        "quality": "240p",
                        "mime": "video\/mp4",
                        "width": 320,
                        "height": 180
                    }
                ],
                "cc": [
                    {
                        "label": "English",
                        "srclang": "en",
                        "src": "\/\/v.tvpage.com\/1758166\/109984974\/cc\/vtt\/en_1504284276.vtt",
                        "default": true
                    }
                ]
            },
            "parentId": "114661406",
            "url": "\/latest-videos\/shark-tank-simply-fit-board\/114661406-109984974"
        },
        {
            "id": "109982803",
            "title": "OXO Good Grips&reg; 2-Quart Batter Bowl",
            "date_created": "1502521280",
            "loginId": "1758166",
            "tags": "",
            "description": "",
            "asset": {
                "user": "",
                "videoMeta": {
                    "duration": "55",
                    "width": 864,
                    "height": 486
                },
                "mediaDuration": "55",
                "prettyDuration": "00:00:55",
                "thumbnailUrl": "\/\/v.tvpage.com\/1758166\/109982803\/537db\/thumb-35a603ad24ee071dae71a2a3df139a96-00001.jpg",
                "type": "mp4",
                "dashUrl": "\/\/v.tvpage.com\/1758166\/109982803\/537db\/media.mpd",
                "hlsUrl": "\/\/v.tvpage.com\/1758166\/109982803\/537db\/media.m3u8",
                "uploadAsset": false,
                "quality": "",
                "sources": [
                    {
                        "file": "\/\/v.tvpage.com\/1758166\/109982803\/537db\/1080p_media.mp4",
                        "quality": "1080p",
                        "mime": "video\/mp4",
                        "width": 864,
                        "height": 486
                    },
                    {
                        "file": "\/\/v.tvpage.com\/1758166\/109982803\/537db\/720p_media.mp4",
                        "quality": "720p",
                        "mime": "video\/mp4",
                        "width": 864,
                        "height": 486
                    },
                    {
                        "file": "\/\/v.tvpage.com\/1758166\/109982803\/537db\/480p_media.mp4",
                        "quality": "480p",
                        "mime": "video\/mp4",
                        "width": 854,
                        "height": 480
                    },
                    {
                        "file": "\/\/v.tvpage.com\/1758166\/109982803\/537db\/360p_media.mp4",
                        "quality": "360p",
                        "mime": "video\/mp4",
                        "width": 640,
                        "height": 360
                    },
                    {
                        "file": "\/\/v.tvpage.com\/1758166\/109982803\/537db\/240p_media.mp4",
                        "quality": "240p",
                        "mime": "video\/mp4",
                        "width": 320,
                        "height": 180
                    }
                ],
                "cc": [
                    {
                        "label": "English",
                        "srclang": "en",
                        "src": "\/\/v.tvpage.com\/1758166\/109982803\/cc\/vtt\/en_1504292444.vtt",
                        "default": true
                    }
                ]
            },
            "parentId": "114661406",
            "url": "\/latest-videos\/oxo-good-grips-2-quart-batter-bowl\/114661406-109982803"
        },
        {
            "id": "111179839",
            "title": "Ionic Pro Turbo Ionic Air Purifier",
            "date_created": "1502923283",
            "loginId": "1758166",
            "tags": "",
            "description": "",
            "asset": {
                "user": "",
                "videoMeta": {
                    "duration": "92",
                    "width": 960,
                    "height": 544
                },
                "sources": [
                    {
                        "file": "\/\/v.tvpage.com\/1758166\/111179839\/d5de8\/1080p_media.mp4",
                        "quality": "1080p",
                        "mime": "video\/mp4",
                        "width": 960,
                        "height": 544
                    },
                    {
                        "file": "\/\/v.tvpage.com\/1758166\/111179839\/d5de8\/720p_media.mp4",
                        "quality": "720p",
                        "mime": "video\/mp4",
                        "width": 960,
                        "height": 544
                    },
                    {
                        "file": "\/\/v.tvpage.com\/1758166\/111179839\/d5de8\/480p_media.mp4",
                        "quality": "480p",
                        "mime": "video\/mp4",
                        "width": 848,
                        "height": 480
                    },
                    {
                        "file": "\/\/v.tvpage.com\/1758166\/111179839\/d5de8\/360p_media.mp4",
                        "quality": "360p",
                        "mime": "video\/mp4",
                        "width": 636,
                        "height": 360
                    },
                    {
                        "file": "\/\/v.tvpage.com\/1758166\/111179839\/d5de8\/240p_media.mp4",
                        "quality": "240p",
                        "mime": "video\/mp4",
                        "width": 320,
                        "height": 182
                    }
                ],
                "mediaDuration": "92",
                "prettyDuration": "00:01:32",
                "thumbnailUrl": "\/\/v.tvpage.com\/1758166\/111179839\/d5de8\/thumb-11521-00002.jpg",
                "type": "mp4",
                "dashUrl": "\/\/v.tvpage.com\/1758166\/111179839\/d5de8\/media.mpd",
                "hlsUrl": "\/\/v.tvpage.com\/1758166\/111179839\/d5de8\/media.m3u8",
                "cc": [
                    {
                        "label": "English",
                        "srclang": "en",
                        "src": "\/\/v.tvpage.com\/1758166\/111179839\/cc\/vtt\/en_1505428378.vtt",
                        "default": true
                    }
                ]
            },
            "parentId": "114661406",
            "url": "\/latest-videos\/ionic-pro-turbo-ionic-air-purifier\/114661406-111179839"
        },
        {
            "id": "109997884",
            "title": "simplehuman Rechargeable Bath Sensor Pump",
            "date_created": "1502524158",
            "loginId": "1758166",
            "tags": "",
            "description": "",
            "asset": {
                "user": "",
                "videoMeta": {
                    "duration": "48",
                    "width": 1920,
                    "height": 1080
                },
                "mediaDuration": "48",
                "prettyDuration": "00:00:48",
                "thumbnailUrl": "\/\/sitecdn.tvpage.com\/live\/users\/1758166\/canvas\/320\/179\/129306841-01320180.jpg",
                "type": "mp4",
                "dashUrl": "\/\/v.tvpage.com\/1758166\/109997884\/1e8b0\/media.mpd",
                "hlsUrl": "\/\/v.tvpage.com\/1758166\/109997884\/1e8b0\/media.m3u8",
                "uploadAsset": false,
                "quality": "",
                "sources": [
                    {
                        "file": "\/\/v.tvpage.com\/1758166\/109997884\/1e8b0\/1080p_media.mp4",
                        "quality": "1080p",
                        "mime": "video\/mp4",
                        "width": 1920,
                        "height": 1080
                    },
                    {
                        "file": "\/\/v.tvpage.com\/1758166\/109997884\/1e8b0\/720p_media.mp4",
                        "quality": "720p",
                        "mime": "video\/mp4",
                        "width": 1280,
                        "height": 720
                    },
                    {
                        "file": "\/\/v.tvpage.com\/1758166\/109997884\/1e8b0\/480p_media.mp4",
                        "quality": "480p",
                        "mime": "video\/mp4",
                        "width": 854,
                        "height": 480
                    },
                    {
                        "file": "\/\/v.tvpage.com\/1758166\/109997884\/1e8b0\/360p_media.mp4",
                        "quality": "360p",
                        "mime": "video\/mp4",
                        "width": 640,
                        "height": 360
                    },
                    {
                        "file": "\/\/v.tvpage.com\/1758166\/109997884\/1e8b0\/240p_media.mp4",
                        "quality": "240p",
                        "mime": "video\/mp4",
                        "width": 320,
                        "height": 180
                    }
                ],
                "cc": [
                    {
                        "label": "English",
                        "srclang": "en",
                        "src": "\/\/v.tvpage.com\/1758166\/109997884\/cc\/vtt\/en_1504810653.vtt",
                        "default": true
                    }
                ]
            },
            "parentId": "114661406",
            "url": "\/latest-videos\/simplehuman-rechargeable-bath-sensor-pump\/114661406-109997884"
        },
        {
            "id": "110006464",
            "title": "shark steam portable pocket",
            "date_created": "1502525562",
            "loginId": "1758166",
            "tags": "",
            "description": "",
            "asset": {
                "user": "",
                "videoMeta": {
                    "duration": "133",
                    "width": 960,
                    "height": 720
                },
                "mediaDuration": "133",
                "prettyDuration": "00:02:13",
                "thumbnailUrl": "\/\/v.tvpage.com\/1758166\/110006464\/77dc9\/thumb-b7d08d96f70aa696ed34006b5b34741e-00002.jpg",
                "type": "mp4",
                "dashUrl": "\/\/v.tvpage.com\/1758166\/110006464\/77dc9\/media.mpd",
                "hlsUrl": "\/\/v.tvpage.com\/1758166\/110006464\/77dc9\/media.m3u8",
                "uploadAsset": false,
                "quality": "",
                "cc": [
                    {
                        "label": "English",
                        "srclang": "en",
                        "src": "\/\/v.tvpage.com\/1758166\/110006464\/cc\/vtt\/en_1517250208.vtt",
                        "default": true
                    }
                ],
                "sources": [
                    {
                        "file": "\/\/v.tvpage.com\/1758166\/110006464\/77dc9\/1080p_media.mp4",
                        "quality": "1080p",
                        "mime": "video\/mp4",
                        "width": 960,
                        "height": 720
                    },
                    {
                        "file": "\/\/v.tvpage.com\/1758166\/110006464\/77dc9\/720p_media.mp4",
                        "quality": "720p",
                        "mime": "video\/mp4",
                        "width": 960,
                        "height": 720
                    },
                    {
                        "file": "\/\/v.tvpage.com\/1758166\/110006464\/77dc9\/480p_media.mp4",
                        "quality": "480p",
                        "mime": "video\/mp4",
                        "width": 640,
                        "height": 480
                    },
                    {
                        "file": "\/\/v.tvpage.com\/1758166\/110006464\/77dc9\/360p_media.mp4",
                        "quality": "360p",
                        "mime": "video\/mp4",
                        "width": 480,
                        "height": 360
                    },
                    {
                        "file": "\/\/v.tvpage.com\/1758166\/110006464\/77dc9\/240p_media.mp4",
                        "quality": "240p",
                        "mime": "video\/mp4",
                        "width": 320,
                        "height": 240
                    }
                ]
            },
            "parentId": "114661406",
            "url": "\/latest-videos\/shark-steam-portable-pocket\/114661406-110006464"
        },
        {
            "id": "109996849",
            "title": "Perfecter Fusion Hair Styler",
            "date_created": "1502524052",
            "loginId": "1758166",
            "tags": "",
            "description": "",
            "asset": {
                "user": "",
                "videoMeta": {
                    "duration": "73",
                    "width": 640,
                    "height": 426
                },
                "mediaDuration": "73",
                "prettyDuration": "00:01:13",
                "thumbnailUrl": "\/\/v.tvpage.com\/1758166\/109996849\/253fb\/thumb-df7118f3a254036278751b5603a3ee22-00002.jpg",
                "type": "mp4",
                "dashUrl": "\/\/v.tvpage.com\/1758166\/109996849\/253fb\/media.mpd",
                "hlsUrl": "\/\/v.tvpage.com\/1758166\/109996849\/253fb\/media.m3u8",
                "uploadAsset": false,
                "quality": "",
                "sources": [
                    {
                        "file": "\/\/v.tvpage.com\/1758166\/109996849\/253fb\/1080p_media.mp4",
                        "quality": "1080p",
                        "mime": "video\/mp4",
                        "width": 640,
                        "height": 426
                    },
                    {
                        "file": "\/\/v.tvpage.com\/1758166\/109996849\/253fb\/720p_media.mp4",
                        "quality": "720p",
                        "mime": "video\/mp4",
                        "width": 640,
                        "height": 426
                    },
                    {
                        "file": "\/\/v.tvpage.com\/1758166\/109996849\/253fb\/480p_media.mp4",
                        "quality": "480p",
                        "mime": "video\/mp4",
                        "width": 640,
                        "height": 426
                    },
                    {
                        "file": "\/\/v.tvpage.com\/1758166\/109996849\/253fb\/360p_media.mp4",
                        "quality": "360p",
                        "mime": "video\/mp4",
                        "width": 540,
                        "height": 360
                    },
                    {
                        "file": "\/\/v.tvpage.com\/1758166\/109996849\/253fb\/240p_media.mp4",
                        "quality": "240p",
                        "mime": "video\/mp4",
                        "width": 320,
                        "height": 212
                    }
                ],
                "cc": [
                    {
                        "label": "English",
                        "srclang": "en",
                        "src": "\/\/v.tvpage.com\/1758166\/109996849\/cc\/vtt\/en_1504226277.vtt",
                        "default": true
                    }
                ]
            },
            "parentId": "114661406",
            "url": "\/latest-videos\/perfecter-fusion-hair-styler\/114661406-109996849"
        },
        {
            "id": "111180516",
            "title": "Cuisinart EM 200 Programmable Espresso Maker",
            "date_created": "1502924717",
            "loginId": "1758166",
            "tags": "",
            "description": "",
            "asset": {
                "user": "",
                "videoMeta": {
                    "duration": "219",
                    "width": 480,
                    "height": 270
                },
                "sources": [
                    {
                        "file": "\/\/v.tvpage.com\/1758166\/111180516\/9dad0\/1080p_media.mp4",
                        "quality": "1080p",
                        "mime": "video\/mp4",
                        "width": 480,
                        "height": 270
                    },
                    {
                        "file": "\/\/v.tvpage.com\/1758166\/111180516\/9dad0\/720p_media.mp4",
                        "quality": "720p",
                        "mime": "video\/mp4",
                        "width": 480,
                        "height": 270
                    },
                    {
                        "file": "\/\/v.tvpage.com\/1758166\/111180516\/9dad0\/480p_media.mp4",
                        "quality": "480p",
                        "mime": "video\/mp4",
                        "width": 480,
                        "height": 270
                    },
                    {
                        "file": "\/\/v.tvpage.com\/1758166\/111180516\/9dad0\/360p_media.mp4",
                        "quality": "360p",
                        "mime": "video\/mp4",
                        "width": 480,
                        "height": 270
                    },
                    {
                        "file": "\/\/v.tvpage.com\/1758166\/111180516\/9dad0\/240p_media.mp4",
                        "quality": "240p",
                        "mime": "video\/mp4",
                        "width": 320,
                        "height": 180
                    }
                ],
                "mediaDuration": "219",
                "prettyDuration": "00:03:39",
                "thumbnailUrl": "\/\/v.tvpage.com\/1758166\/111180516\/9dad0\/thumb-5590-00002.jpg",
                "type": "mp4",
                "dashUrl": "\/\/v.tvpage.com\/1758166\/111180516\/9dad0\/media.mpd",
                "hlsUrl": "\/\/v.tvpage.com\/1758166\/111180516\/9dad0\/media.m3u8",
                "cc": [
                    {
                        "label": "English",
                        "srclang": "en",
                        "src": "\/\/v.tvpage.com\/1758166\/111180516\/cc\/vtt\/en_1504135488.vtt",
                        "default": true
                    }
                ]
            },
            "parentId": "114661406",
            "url": "\/latest-videos\/cuisinart-em-200-programmable-espresso-maker\/114661406-111180516"
        },
        {
            "id": "109989221",
            "title": "3 Second Brow&trade; Eyebrow Stamp",
            "date_created": "1502522457",
            "loginId": "1758166",
            "tags": "",
            "description": "",
            "asset": {
                "user": "",
                "videoMeta": {
                    "duration": "54",
                    "width": 1280,
                    "height": 720
                },
                "mediaDuration": "54",
                "prettyDuration": "00:00:54",
                "thumbnailUrl": "\/\/v.tvpage.com\/1758166\/109989221\/a7fcf\/thumb-1d13587d41423286abb74d8f6e4e5480-00001.jpg",
                "type": "mp4",
                "dashUrl": "\/\/v.tvpage.com\/1758166\/109989221\/a7fcf\/media.mpd",
                "hlsUrl": "\/\/v.tvpage.com\/1758166\/109989221\/a7fcf\/media.m3u8",
                "uploadAsset": false,
                "quality": "",
                "sources": [
                    {
                        "file": "\/\/v.tvpage.com\/1758166\/109989221\/a7fcf\/1080p_media.mp4",
                        "quality": "1080p",
                        "mime": "video\/mp4",
                        "width": 1280,
                        "height": 720
                    },
                    {
                        "file": "\/\/v.tvpage.com\/1758166\/109989221\/a7fcf\/720p_media.mp4",
                        "quality": "720p",
                        "mime": "video\/mp4",
                        "width": 1280,
                        "height": 720
                    },
                    {
                        "file": "\/\/v.tvpage.com\/1758166\/109989221\/a7fcf\/480p_media.mp4",
                        "quality": "480p",
                        "mime": "video\/mp4",
                        "width": 854,
                        "height": 480
                    },
                    {
                        "file": "\/\/v.tvpage.com\/1758166\/109989221\/a7fcf\/360p_media.mp4",
                        "quality": "360p",
                        "mime": "video\/mp4",
                        "width": 640,
                        "height": 360
                    },
                    {
                        "file": "\/\/v.tvpage.com\/1758166\/109989221\/a7fcf\/240p_media.mp4",
                        "quality": "240p",
                        "mime": "video\/mp4",
                        "width": 320,
                        "height": 180
                    }
                ],
                "cc": [
                    {
                        "label": "English",
                        "srclang": "en",
                        "src": "\/\/v.tvpage.com\/1758166\/109989221\/cc\/vtt\/en_1504207609.vtt",
                        "default": true
                    }
                ]
            },
            "parentId": "114661406",
            "url": "\/latest-videos\/3-second-brow-eyebrow-stamp\/114661406-109989221"
        },
        {
            "id": "111180544",
            "title": "Cuisinart TOB 195 Convection Toaster Oven Broiler",
            "date_created": "1502924743",
            "loginId": "1758166",
            "tags": "",
            "description": "",
            "asset": {
                "user": "",
                "videoMeta": {
                    "duration": "112",
                    "width": 480,
                    "height": 270
                },
                "sources": [
                    {
                        "file": "\/\/v.tvpage.com\/1758166\/111180544\/3fabf\/1080p_media.mp4",
                        "quality": "1080p",
                        "mime": "video\/mp4",
                        "width": 480,
                        "height": 270
                    },
                    {
                        "file": "\/\/v.tvpage.com\/1758166\/111180544\/3fabf\/720p_media.mp4",
                        "quality": "720p",
                        "mime": "video\/mp4",
                        "width": 480,
                        "height": 270
                    },
                    {
                        "file": "\/\/v.tvpage.com\/1758166\/111180544\/3fabf\/480p_media.mp4",
                        "quality": "480p",
                        "mime": "video\/mp4",
                        "width": 480,
                        "height": 270
                    },
                    {
                        "file": "\/\/v.tvpage.com\/1758166\/111180544\/3fabf\/360p_media.mp4",
                        "quality": "360p",
                        "mime": "video\/mp4",
                        "width": 480,
                        "height": 270
                    },
                    {
                        "file": "\/\/v.tvpage.com\/1758166\/111180544\/3fabf\/240p_media.mp4",
                        "quality": "240p",
                        "mime": "video\/mp4",
                        "width": 320,
                        "height": 180
                    }
                ],
                "mediaDuration": "112",
                "prettyDuration": "00:01:52",
                "thumbnailUrl": "\/\/v.tvpage.com\/1758166\/111180544\/3fabf\/thumb-5669-00002.jpg",
                "type": "mp4",
                "dashUrl": "\/\/v.tvpage.com\/1758166\/111180544\/3fabf\/media.mpd",
                "hlsUrl": "\/\/v.tvpage.com\/1758166\/111180544\/3fabf\/media.m3u8",
                "cc": [
                    {
                        "label": "English",
                        "srclang": "en",
                        "src": "\/\/v.tvpage.com\/1758166\/111180544\/cc\/vtt\/en_1504121198.vtt",
                        "default": true
                    }
                ]
            },
            "parentId": "114661406",
            "url": "\/latest-videos\/cuisinart-tob-195-convection-toaster-oven-broiler\/114661406-111180544"
        },
        {
            "id": "109992385",
            "title": "Coravin&trade; Model Eight Wine System",
            "date_created": "1502522979",
            "loginId": "1758166",
            "tags": "",
            "description": "",
            "asset": {
                "user": "",
                "videoMeta": {
                    "duration": "47",
                    "width": 1280,
                    "height": 720
                },
                "mediaDuration": "47",
                "prettyDuration": "00:00:47",
                "thumbnailUrl": "\/\/sitecdn.tvpage.com\/live\/users\/1758166\/canvas\/320\/179\/198079809-01320180.jpg",
                "type": "mp4",
                "dashUrl": "\/\/v.tvpage.com\/1758166\/109992385\/5d801\/media.mpd",
                "hlsUrl": "\/\/v.tvpage.com\/1758166\/109992385\/5d801\/media.m3u8",
                "uploadAsset": false,
                "quality": "",
                "cc": [
                    {
                        "label": "English",
                        "srclang": "en",
                        "src": "\/\/v.tvpage.com\/1758166\/109992385\/cc\/vtt\/en_1504293700.vtt",
                        "default": true
                    }
                ],
                "sources": [
                    {
                        "file": "\/\/v.tvpage.com\/1758166\/109992385\/5d801\/1080p_media.mp4",
                        "quality": "1080p",
                        "mime": "video\/mp4",
                        "width": 1280,
                        "height": 720
                    },
                    {
                        "file": "\/\/v.tvpage.com\/1758166\/109992385\/5d801\/720p_media.mp4",
                        "quality": "720p",
                        "mime": "video\/mp4",
                        "width": 1280,
                        "height": 720
                    },
                    {
                        "file": "\/\/v.tvpage.com\/1758166\/109992385\/5d801\/480p_media.mp4",
                        "quality": "480p",
                        "mime": "video\/mp4",
                        "width": 854,
                        "height": 480
                    },
                    {
                        "file": "\/\/v.tvpage.com\/1758166\/109992385\/5d801\/360p_media.mp4",
                        "quality": "360p",
                        "mime": "video\/mp4",
                        "width": 640,
                        "height": 360
                    },
                    {
                        "file": "\/\/v.tvpage.com\/1758166\/109992385\/5d801\/240p_media.mp4",
                        "quality": "240p",
                        "mime": "video\/mp4",
                        "width": 320,
                        "height": 180
                    }
                ]
            },
            "parentId": "114661406",
            "url": "\/latest-videos\/coravin-model-eight-wine-system\/114661406-109992385"
        },
        {
            "id": "109974333",
            "title": "Wilton Armetale&reg; Gourmet&trade; Grillware",
            "date_created": "1502519922",
            "loginId": "1758166",
            "tags": "",
            "description": "",
            "asset": {
                "user": "",
                "videoMeta": "1362607051",
                "thumbnailUrl": "\/\/sitecdn.tvpage.com\/live\/users\/1758166\/canvas\/320\/179\/825928114-01320180.jpg",
                "uploadAsset": false,
                "quality": ""
            },
            "parentId": "114661406",
            "url": "\/latest-videos\/wilton-armetale-gourmet-grillware\/114661406-109974333"
        },
        {
            "id": "109979521",
            "title": "Shark&reg; Rocket&reg; Complete TruePet&reg; Ultra-Light Upright with DuoClean&trade;",
            "date_created": "1502520466",
            "loginId": "1758166",
            "tags": "",
            "description": "",
            "asset": {
                "user": "",
                "videoMeta": {
                    "duration": "87",
                    "width": 1280,
                    "height": 720
                },
                "mediaDuration": "87",
                "prettyDuration": "00:01:27",
                "thumbnailUrl": "\/\/v.tvpage.com\/1758166\/109979521\/cf73e\/thumb-0f4521a073b174ef6f077c5ed10236fd-00002.jpg",
                "type": "mp4",
                "dashUrl": "\/\/v.tvpage.com\/1758166\/109979521\/cf73e\/media.mpd",
                "hlsUrl": "\/\/v.tvpage.com\/1758166\/109979521\/cf73e\/media.m3u8",
                "uploadAsset": false,
                "quality": "",
                "sources": [
                    {
                        "file": "\/\/v.tvpage.com\/1758166\/109979521\/cf73e\/1080p_media.mp4",
                        "quality": "1080p",
                        "mime": "video\/mp4",
                        "width": 1280,
                        "height": 720
                    },
                    {
                        "file": "\/\/v.tvpage.com\/1758166\/109979521\/cf73e\/720p_media.mp4",
                        "quality": "720p",
                        "mime": "video\/mp4",
                        "width": 1280,
                        "height": 720
                    },
                    {
                        "file": "\/\/v.tvpage.com\/1758166\/109979521\/cf73e\/480p_media.mp4",
                        "quality": "480p",
                        "mime": "video\/mp4",
                        "width": 854,
                        "height": 480
                    },
                    {
                        "file": "\/\/v.tvpage.com\/1758166\/109979521\/cf73e\/360p_media.mp4",
                        "quality": "360p",
                        "mime": "video\/mp4",
                        "width": 640,
                        "height": 360
                    },
                    {
                        "file": "\/\/v.tvpage.com\/1758166\/109979521\/cf73e\/240p_media.mp4",
                        "quality": "240p",
                        "mime": "video\/mp4",
                        "width": 320,
                        "height": 180
                    }
                ],
                "cc": [
                    {
                        "label": "English",
                        "srclang": "en",
                        "src": "\/\/v.tvpage.com\/1758166\/109979521\/cc\/vtt\/en_1504284532.vtt",
                        "default": true
                    }
                ]
            },
            "parentId": "114661406",
            "url": "\/latest-videos\/shark-rocket-complete-truepet-ultra-light-upright-with-duoclean\/114661406-109979521"
        },
        {
            "id": "109991373",
            "title": "Sure Fit Slipcover - How to Install",
            "date_created": "1502522929",
            "loginId": "1758166",
            "tags": "",
            "description": "",
            "asset": {
                "user": "",
                "videoMeta": {
                    "duration": "115",
                    "width": 1280,
                    "height": 720
                },
                "mediaDuration": "115",
                "prettyDuration": "00:01:55",
                "thumbnailUrl": "\/\/v.tvpage.com\/1758166\/109991373\/ad6a5\/thumb-f548f7bdc82d2e9b812c73eb885ab1c3-00002.jpg",
                "type": "mp4",
                "dashUrl": "\/\/v.tvpage.com\/1758166\/109991373\/ad6a5\/media.mpd",
                "hlsUrl": "\/\/v.tvpage.com\/1758166\/109991373\/ad6a5\/media.m3u8",
                "uploadAsset": false,
                "quality": "",
                "cc": [
                    {
                        "label": "English",
                        "srclang": "en",
                        "src": "\/\/v.tvpage.com\/1758166\/109991373\/cc\/vtt\/en_1516736749.vtt",
                        "default": true
                    }
                ],
                "sources": [
                    {
                        "file": "\/\/v.tvpage.com\/1758166\/109991373\/ad6a5\/1080p_media.mp4",
                        "quality": "1080p",
                        "mime": "video\/mp4",
                        "width": 1280,
                        "height": 720
                    },
                    {
                        "file": "\/\/v.tvpage.com\/1758166\/109991373\/ad6a5\/720p_media.mp4",
                        "quality": "720p",
                        "mime": "video\/mp4",
                        "width": 1280,
                        "height": 720
                    },
                    {
                        "file": "\/\/v.tvpage.com\/1758166\/109991373\/ad6a5\/480p_media.mp4",
                        "quality": "480p",
                        "mime": "video\/mp4",
                        "width": 854,
                        "height": 480
                    },
                    {
                        "file": "\/\/v.tvpage.com\/1758166\/109991373\/ad6a5\/360p_media.mp4",
                        "quality": "360p",
                        "mime": "video\/mp4",
                        "width": 640,
                        "height": 360
                    },
                    {
                        "file": "\/\/v.tvpage.com\/1758166\/109991373\/ad6a5\/240p_media.mp4",
                        "quality": "240p",
                        "mime": "video\/mp4",
                        "width": 320,
                        "height": 180
                    }
                ]
            },
            "parentId": "114661406",
            "url": "\/latest-videos\/sure-fit-slipcover\/114661406-109991373"
        },
        {
            "id": "110002100",
            "title": "simplehuman&reg; Dual Compartment Rectangular 15.3-Gallon Step Can",
            "date_created": "1502524784",
            "loginId": "1758166",
            "tags": "",
            "description": "",
            "asset": {
                "user": "",
                "videoMeta": {
                    "duration": "11",
                    "width": 1920,
                    "height": 1080
                },
                "mediaDuration": "11",
                "prettyDuration": "00:00:11",
                "thumbnailUrl": "\/\/v.tvpage.com\/1758166\/110002100\/42f32\/thumb-5f0d13d5b5282b44124272fe74936343-00001.jpg",
                "type": "mp4",
                "dashUrl": "\/\/v.tvpage.com\/1758166\/110002100\/42f32\/media.mpd",
                "hlsUrl": "\/\/v.tvpage.com\/1758166\/110002100\/42f32\/media.m3u8",
                "uploadAsset": false,
                "quality": "",
                "sources": [
                    {
                        "file": "\/\/v.tvpage.com\/1758166\/110002100\/42f32\/1080p_media.mp4",
                        "quality": "1080p",
                        "mime": "video\/mp4",
                        "width": 1920,
                        "height": 1080
                    },
                    {
                        "file": "\/\/v.tvpage.com\/1758166\/110002100\/42f32\/720p_media.mp4",
                        "quality": "720p",
                        "mime": "video\/mp4",
                        "width": 1280,
                        "height": 720
                    },
                    {
                        "file": "\/\/v.tvpage.com\/1758166\/110002100\/42f32\/480p_media.mp4",
                        "quality": "480p",
                        "mime": "video\/mp4",
                        "width": 854,
                        "height": 480
                    },
                    {
                        "file": "\/\/v.tvpage.com\/1758166\/110002100\/42f32\/360p_media.mp4",
                        "quality": "360p",
                        "mime": "video\/mp4",
                        "width": 640,
                        "height": 360
                    },
                    {
                        "file": "\/\/v.tvpage.com\/1758166\/110002100\/42f32\/240p_media.mp4",
                        "quality": "240p",
                        "mime": "video\/mp4",
                        "width": 320,
                        "height": 180
                    }
                ],
                "cc": [
                    {
                        "label": "English",
                        "srclang": "en",
                        "src": "\/\/v.tvpage.com\/1758166\/110002100\/cc\/vtt\/en_1504039682.vtt",
                        "default": true
                    }
                ]
            },
            "parentId": "114661406",
            "url": "\/latest-videos\/simplehuman-dual-compartment-rectangular-15-3-gallon-step-can\/114661406-110002100"
        },
        {
            "id": "111179826",
            "title": "NuWave Pro Infrared Oven",
            "date_created": "1502923264",
            "loginId": "1758166",
            "tags": "",
            "description": "",
            "asset": {
                "user": "",
                "videoMeta": {
                    "duration": "123",
                    "width": 960,
                    "height": 544
                },
                "sources": [
                    {
                        "file": "\/\/v.tvpage.com\/1758166\/111179826\/f49c6\/1080p_media.mp4",
                        "quality": "1080p",
                        "mime": "video\/mp4",
                        "width": 960,
                        "height": 544
                    },
                    {
                        "file": "\/\/v.tvpage.com\/1758166\/111179826\/f49c6\/720p_media.mp4",
                        "quality": "720p",
                        "mime": "video\/mp4",
                        "width": 960,
                        "height": 544
                    },
                    {
                        "file": "\/\/v.tvpage.com\/1758166\/111179826\/f49c6\/480p_media.mp4",
                        "quality": "480p",
                        "mime": "video\/mp4",
                        "width": 848,
                        "height": 480
                    },
                    {
                        "file": "\/\/v.tvpage.com\/1758166\/111179826\/f49c6\/360p_media.mp4",
                        "quality": "360p",
                        "mime": "video\/mp4",
                        "width": 636,
                        "height": 360
                    },
                    {
                        "file": "\/\/v.tvpage.com\/1758166\/111179826\/f49c6\/240p_media.mp4",
                        "quality": "240p",
                        "mime": "video\/mp4",
                        "width": 320,
                        "height": 182
                    }
                ],
                "mediaDuration": "123",
                "prettyDuration": "00:02:03",
                "thumbnailUrl": "\/\/v.tvpage.com\/1758166\/111179826\/f49c6\/thumb-11487-00002.jpg",
                "type": "mp4",
                "dashUrl": "\/\/v.tvpage.com\/1758166\/111179826\/f49c6\/media.mpd",
                "hlsUrl": "\/\/v.tvpage.com\/1758166\/111179826\/f49c6\/media.m3u8",
                "cc": [
                    {
                        "label": "English",
                        "srclang": "en",
                        "src": "\/\/v.tvpage.com\/1758166\/111179826\/cc\/vtt\/en_1504132846.vtt",
                        "default": true
                    }
                ]
            },
            "parentId": "114661406",
            "url": "\/latest-videos\/nuwave-pro-infrared-oven\/114661406-111179826"
        },
        {
            "id": "111179784",
            "title": "Breville Smart Oven Accessories BOV800CB",
            "date_created": "1502923128",
            "loginId": "1758166",
            "tags": "",
            "description": "",
            "asset": {
                "user": "",
                "videoMeta": {
                    "duration": "93",
                    "width": 1280,
                    "height": 720
                },
                "mediaDuration": "93",
                "prettyDuration": "00:01:33",
                "thumbnailUrl": "\/\/v.tvpage.com\/1758166\/111179784\/f1417\/thumb-11270-00002.jpg",
                "type": "mp4",
                "dashUrl": "\/\/v.tvpage.com\/1758166\/111179784\/f1417\/media.mpd",
                "hlsUrl": "\/\/v.tvpage.com\/1758166\/111179784\/f1417\/media.m3u8",
                "cc": [
                    {
                        "label": "English",
                        "srclang": "en",
                        "src": "\/\/v.tvpage.com\/1758166\/111179784\/cc\/vtt\/en_1505428510.vtt",
                        "default": true
                    }
                ],
                "uploadAsset": false,
                "quality": "",
                "sources": [
                    {
                        "file": "\/\/v.tvpage.com\/1758166\/111179784\/f1417\/1080p_media.mp4",
                        "quality": "1080p",
                        "mime": "video\/mp4",
                        "width": 1280,
                        "height": 720
                    },
                    {
                        "file": "\/\/v.tvpage.com\/1758166\/111179784\/f1417\/720p_media.mp4",
                        "quality": "720p",
                        "mime": "video\/mp4",
                        "width": 1280,
                        "height": 720
                    },
                    {
                        "file": "\/\/v.tvpage.com\/1758166\/111179784\/f1417\/480p_media.mp4",
                        "quality": "480p",
                        "mime": "video\/mp4",
                        "width": 854,
                        "height": 480
                    },
                    {
                        "file": "\/\/v.tvpage.com\/1758166\/111179784\/f1417\/360p_media.mp4",
                        "quality": "360p",
                        "mime": "video\/mp4",
                        "width": 640,
                        "height": 360
                    },
                    {
                        "file": "\/\/v.tvpage.com\/1758166\/111179784\/f1417\/240p_media.mp4",
                        "quality": "240p",
                        "mime": "video\/mp4",
                        "width": 320,
                        "height": 180
                    }
                ]
            },
            "parentId": "114661406",
            "url": "\/latest-videos\/breville-smart-oven-accessories-bov800cb\/114661406-111179784"
        }
    ]
}