{
    "pageNumber": 19,
    "data": [
        {
            "id": "158904780",
            "title": "Close Ties Natural Fit Carrier\u2122 - See it in Action",
            "date_created": "1523486866",
            "loginId": "1758166",
            "tags": "",
            "description": "",
            "asset": {
                "user": {
                    "firstName": "",
                    "lastName": "",
                    "emailAddress": ""
                },
                "videoMeta": {
                    "duration": "106",
                    "width": 1280,
                    "height": 720
                },
                "mediaDuration": "106",
                "prettyDuration": "00:01:46",
                "thumbnailUrl": "\/\/v.tvpage.com\/1758166\/158904780\/58119\/thumb-1acffaeb646ab4c2768aea44cc1db977-00002.jpg",
                "type": "mp4",
                "dashUrl": "\/\/v.tvpage.com\/1758166\/158904780\/58119\/media.mpd",
                "hlsUrl": "\/\/v.tvpage.com\/1758166\/158904780\/58119\/media.m3u8",
                "uploadAsset": false,
                "quality": "",
                "cc": [
                    {
                        "label": "English",
                        "srclang": "en",
                        "src": "\/\/v.tvpage.com\/1758166\/158904780\/cc\/vtt\/en_1524158959.vtt",
                        "default": true
                    }
                ],
                "sources": [
                    {
                        "file": "\/\/v.tvpage.com\/1758166\/158904780\/58119\/1080p_media.mp4",
                        "quality": "1080p",
                        "mime": "video\/mp4",
                        "width": 1280,
                        "height": 720
                    },
                    {
                        "file": "\/\/v.tvpage.com\/1758166\/158904780\/58119\/720p_media.mp4",
                        "quality": "720p",
                        "mime": "video\/mp4",
                        "width": 1280,
                        "height": 720
                    },
                    {
                        "file": "\/\/v.tvpage.com\/1758166\/158904780\/58119\/480p_media.mp4",
                        "quality": "480p",
                        "mime": "video\/mp4",
                        "width": 854,
                        "height": 480
                    },
                    {
                        "file": "\/\/v.tvpage.com\/1758166\/158904780\/58119\/360p_media.mp4",
                        "quality": "360p",
                        "mime": "video\/mp4",
                        "width": 640,
                        "height": 360
                    },
                    {
                        "file": "\/\/v.tvpage.com\/1758166\/158904780\/58119\/240p_media.mp4",
                        "quality": "240p",
                        "mime": "video\/mp4",
                        "width": 320,
                        "height": 180
                    }
                ]
            },
            "parentId": "114661406",
            "url": "\/latest-videos\/close-ties-natural-fit-carrier-see-it-in-action\/114661406-158904780"
        },
        {
            "id": "158904781",
            "title": "Cuddle Up\u2122 Ergonomic Hood Carrier  - See It In Action",
            "date_created": "1523486871",
            "loginId": "1758166",
            "tags": "",
            "description": "",
            "asset": {
                "user": {
                    "firstName": "",
                    "lastName": "",
                    "emailAddress": ""
                },
                "videoMeta": {
                    "duration": "47",
                    "width": 1280,
                    "height": 720
                },
                "mediaDuration": "47",
                "prettyDuration": "00:00:47",
                "thumbnailUrl": "\/\/sitecdn.tvpage.com\/live\/users\/1758166\/canvas\/1920\/1080\/899970989-1523490122.jpg",
                "type": "mp4",
                "dashUrl": "\/\/v.tvpage.com\/1758166\/158904781\/3968e\/media.mpd",
                "hlsUrl": "\/\/v.tvpage.com\/1758166\/158904781\/3968e\/media.m3u8",
                "uploadAsset": false,
                "quality": "",
                "cc": [
                    {
                        "label": "English",
                        "srclang": "en",
                        "src": "\/\/v.tvpage.com\/1758166\/158904781\/cc\/vtt\/en_1524158893.vtt",
                        "default": true
                    }
                ],
                "sources": [
                    {
                        "file": "\/\/v.tvpage.com\/1758166\/158904781\/3968e\/1080p_media.mp4",
                        "quality": "1080p",
                        "mime": "video\/mp4",
                        "width": 1280,
                        "height": 720
                    },
                    {
                        "file": "\/\/v.tvpage.com\/1758166\/158904781\/3968e\/720p_media.mp4",
                        "quality": "720p",
                        "mime": "video\/mp4",
                        "width": 1280,
                        "height": 720
                    },
                    {
                        "file": "\/\/v.tvpage.com\/1758166\/158904781\/3968e\/480p_media.mp4",
                        "quality": "480p",
                        "mime": "video\/mp4",
                        "width": 854,
                        "height": 480
                    },
                    {
                        "file": "\/\/v.tvpage.com\/1758166\/158904781\/3968e\/360p_media.mp4",
                        "quality": "360p",
                        "mime": "video\/mp4",
                        "width": 640,
                        "height": 360
                    },
                    {
                        "file": "\/\/v.tvpage.com\/1758166\/158904781\/3968e\/240p_media.mp4",
                        "quality": "240p",
                        "mime": "video\/mp4",
                        "width": 320,
                        "height": 180
                    }
                ]
            },
            "parentId": "114661406",
            "url": "\/latest-videos\/cuddle-up-ergonomic-hood-carrier-see-it-in-action\/114661406-158904781"
        },
        {
            "id": "158904782",
            "title": "Fresh Squeezed Line Demo - How to use the Infantino Squeeze Station",
            "date_created": "1523486881",
            "loginId": "1758166",
            "tags": "",
            "description": "",
            "asset": {
                "user": {
                    "firstName": "",
                    "lastName": "",
                    "emailAddress": ""
                },
                "videoMeta": {
                    "duration": "274",
                    "width": 1280,
                    "height": 720
                },
                "mediaDuration": "274",
                "prettyDuration": "00:04:34",
                "thumbnailUrl": "\/\/v.tvpage.com\/1758166\/158904782\/797bb\/thumb-53a88246d433e9becf5ea4fbb1d3e348-00002.jpg",
                "type": "mp4",
                "dashUrl": "\/\/v.tvpage.com\/1758166\/158904782\/797bb\/media.mpd",
                "hlsUrl": "\/\/v.tvpage.com\/1758166\/158904782\/797bb\/media.m3u8",
                "uploadAsset": false,
                "quality": "",
                "cc": [
                    {
                        "label": "English",
                        "srclang": "en",
                        "src": "\/\/v.tvpage.com\/1758166\/158904782\/cc\/vtt\/en_1524158830.vtt",
                        "default": true
                    }
                ],
                "sources": [
                    {
                        "file": "\/\/v.tvpage.com\/1758166\/158904782\/797bb\/1080p_media.mp4",
                        "quality": "1080p",
                        "mime": "video\/mp4",
                        "width": 1280,
                        "height": 720
                    },
                    {
                        "file": "\/\/v.tvpage.com\/1758166\/158904782\/797bb\/720p_media.mp4",
                        "quality": "720p",
                        "mime": "video\/mp4",
                        "width": 1280,
                        "height": 720
                    },
                    {
                        "file": "\/\/v.tvpage.com\/1758166\/158904782\/797bb\/480p_media.mp4",
                        "quality": "480p",
                        "mime": "video\/mp4",
                        "width": 854,
                        "height": 480
                    },
                    {
                        "file": "\/\/v.tvpage.com\/1758166\/158904782\/797bb\/360p_media.mp4",
                        "quality": "360p",
                        "mime": "video\/mp4",
                        "width": 640,
                        "height": 360
                    },
                    {
                        "file": "\/\/v.tvpage.com\/1758166\/158904782\/797bb\/240p_media.mp4",
                        "quality": "240p",
                        "mime": "video\/mp4",
                        "width": 320,
                        "height": 180
                    }
                ]
            },
            "parentId": "114661406",
            "url": "\/latest-videos\/fresh-squeezed-line-demo-how-to-use-the-infantino-squeeze-station\/114661406-158904782"
        },
        {
            "id": "158904783",
            "title": "Pressure Cooker Corned Beef | Crock-Pot\u00ae Express Crock",
            "date_created": "1523486885",
            "loginId": "1758166",
            "tags": "",
            "description": "",
            "asset": {
                "user": {
                    "firstName": "",
                    "lastName": "",
                    "emailAddress": ""
                },
                "videoMeta": {
                    "duration": "40",
                    "width": 1280,
                    "height": 720
                },
                "mediaDuration": "40",
                "prettyDuration": "00:00:40",
                "thumbnailUrl": "\/\/sitecdn.tvpage.com\/live\/users\/1758166\/canvas\/1920\/1080\/813540038-1523490086.jpg",
                "type": "mp4",
                "dashUrl": "\/\/v.tvpage.com\/1758166\/158904783\/0214f\/media.mpd",
                "hlsUrl": "\/\/v.tvpage.com\/1758166\/158904783\/0214f\/media.m3u8",
                "uploadAsset": false,
                "quality": "",
                "cc": [
                    {
                        "label": "English",
                        "srclang": "en",
                        "src": "\/\/v.tvpage.com\/1758166\/158904783\/cc\/vtt\/en_1524158784.vtt",
                        "default": true
                    }
                ],
                "sources": [
                    {
                        "file": "\/\/v.tvpage.com\/1758166\/158904783\/0214f\/1080p_media.mp4",
                        "quality": "1080p",
                        "mime": "video\/mp4",
                        "width": 1280,
                        "height": 720
                    },
                    {
                        "file": "\/\/v.tvpage.com\/1758166\/158904783\/0214f\/720p_media.mp4",
                        "quality": "720p",
                        "mime": "video\/mp4",
                        "width": 1280,
                        "height": 720
                    },
                    {
                        "file": "\/\/v.tvpage.com\/1758166\/158904783\/0214f\/480p_media.mp4",
                        "quality": "480p",
                        "mime": "video\/mp4",
                        "width": 854,
                        "height": 480
                    },
                    {
                        "file": "\/\/v.tvpage.com\/1758166\/158904783\/0214f\/360p_media.mp4",
                        "quality": "360p",
                        "mime": "video\/mp4",
                        "width": 640,
                        "height": 360
                    },
                    {
                        "file": "\/\/v.tvpage.com\/1758166\/158904783\/0214f\/240p_media.mp4",
                        "quality": "240p",
                        "mime": "video\/mp4",
                        "width": 320,
                        "height": 180
                    }
                ]
            },
            "parentId": "114661406",
            "url": "\/latest-videos\/pressure-cooker-corned-beef-crock-pot-express-crock\/114661406-158904783"
        },
        {
            "id": "158904784",
            "title": "How To Use the Touchscreen Digital Controls | Crock-Pot\u00ae",
            "date_created": "1523486894",
            "loginId": "1758166",
            "tags": "",
            "description": "",
            "asset": {
                "user": {
                    "firstName": "",
                    "lastName": "",
                    "emailAddress": ""
                },
                "videoMeta": {
                    "duration": "150",
                    "width": 1280,
                    "height": 720
                },
                "mediaDuration": "150",
                "prettyDuration": "00:02:30",
                "thumbnailUrl": "\/\/v.tvpage.com\/1758166\/158904784\/757ed\/thumb-6f8b4ca11f37ce6b907724507deb7c0c-00002.jpg",
                "type": "mp4",
                "dashUrl": "\/\/v.tvpage.com\/1758166\/158904784\/757ed\/media.mpd",
                "hlsUrl": "\/\/v.tvpage.com\/1758166\/158904784\/757ed\/media.m3u8",
                "uploadAsset": false,
                "quality": "",
                "cc": [
                    {
                        "label": "English",
                        "srclang": "en",
                        "src": "\/\/v.tvpage.com\/1758166\/158904784\/cc\/vtt\/en_1524158743.vtt",
                        "default": true
                    }
                ],
                "sources": [
                    {
                        "file": "\/\/v.tvpage.com\/1758166\/158904784\/757ed\/1080p_media.mp4",
                        "quality": "1080p",
                        "mime": "video\/mp4",
                        "width": 1280,
                        "height": 720
                    },
                    {
                        "file": "\/\/v.tvpage.com\/1758166\/158904784\/757ed\/720p_media.mp4",
                        "quality": "720p",
                        "mime": "video\/mp4",
                        "width": 1280,
                        "height": 720
                    },
                    {
                        "file": "\/\/v.tvpage.com\/1758166\/158904784\/757ed\/480p_media.mp4",
                        "quality": "480p",
                        "mime": "video\/mp4",
                        "width": 854,
                        "height": 480
                    },
                    {
                        "file": "\/\/v.tvpage.com\/1758166\/158904784\/757ed\/360p_media.mp4",
                        "quality": "360p",
                        "mime": "video\/mp4",
                        "width": 640,
                        "height": 360
                    },
                    {
                        "file": "\/\/v.tvpage.com\/1758166\/158904784\/757ed\/240p_media.mp4",
                        "quality": "240p",
                        "mime": "video\/mp4",
                        "width": 320,
                        "height": 180
                    }
                ]
            },
            "parentId": "114661406",
            "url": "\/latest-videos\/how-to-use-the-touchscreen-digital-controls-crock-pot\/114661406-158904784"
        },
        {
            "id": "158904785",
            "title": "How To Use the Smart-Pot\u00ae Digital Controls | Crock-Pot\u00ae",
            "date_created": "1523486902",
            "loginId": "1758166",
            "tags": "",
            "description": "",
            "asset": {
                "user": {
                    "firstName": "",
                    "lastName": "",
                    "emailAddress": ""
                },
                "videoMeta": {
                    "duration": "124",
                    "width": 1280,
                    "height": 720
                },
                "mediaDuration": "124",
                "prettyDuration": "00:02:04",
                "thumbnailUrl": "\/\/v.tvpage.com\/1758166\/158904785\/20727\/thumb-a536c7d6a85db0dee70d441f3c04af22-00002.jpg",
                "type": "mp4",
                "dashUrl": "\/\/v.tvpage.com\/1758166\/158904785\/20727\/media.mpd",
                "hlsUrl": "\/\/v.tvpage.com\/1758166\/158904785\/20727\/media.m3u8",
                "uploadAsset": false,
                "quality": "",
                "cc": [
                    {
                        "label": "English",
                        "srclang": "en",
                        "src": "\/\/v.tvpage.com\/1758166\/158904785\/cc\/vtt\/en_1524158684.vtt",
                        "default": true
                    }
                ],
                "sources": [
                    {
                        "file": "\/\/v.tvpage.com\/1758166\/158904785\/20727\/1080p_media.mp4",
                        "quality": "1080p",
                        "mime": "video\/mp4",
                        "width": 1280,
                        "height": 720
                    },
                    {
                        "file": "\/\/v.tvpage.com\/1758166\/158904785\/20727\/720p_media.mp4",
                        "quality": "720p",
                        "mime": "video\/mp4",
                        "width": 1280,
                        "height": 720
                    },
                    {
                        "file": "\/\/v.tvpage.com\/1758166\/158904785\/20727\/480p_media.mp4",
                        "quality": "480p",
                        "mime": "video\/mp4",
                        "width": 854,
                        "height": 480
                    },
                    {
                        "file": "\/\/v.tvpage.com\/1758166\/158904785\/20727\/360p_media.mp4",
                        "quality": "360p",
                        "mime": "video\/mp4",
                        "width": 640,
                        "height": 360
                    },
                    {
                        "file": "\/\/v.tvpage.com\/1758166\/158904785\/20727\/240p_media.mp4",
                        "quality": "240p",
                        "mime": "video\/mp4",
                        "width": 320,
                        "height": 180
                    }
                ]
            },
            "parentId": "114661406",
            "url": "\/latest-videos\/how-to-use-the-smart-pot-digital-controls-crock-pot\/114661406-158904785"
        },
        {
            "id": "158904786",
            "title": "Fishtail Chignon Hair Braid Tutorial | Prom Hairstyles | Garnier Fructis Style",
            "date_created": "1523486910",
            "loginId": "1758166",
            "tags": "",
            "description": "",
            "asset": {
                "user": {
                    "firstName": "",
                    "lastName": "",
                    "emailAddress": ""
                },
                "videoMeta": {
                    "duration": "92",
                    "width": 1280,
                    "height": 720
                },
                "mediaDuration": "92",
                "prettyDuration": "00:01:32",
                "thumbnailUrl": "\/\/v.tvpage.com\/1758166\/158904786\/ca2d5\/thumb-8b401ba616903bea25445a52bd383fcd-00002.jpg",
                "type": "mp4",
                "dashUrl": "\/\/v.tvpage.com\/1758166\/158904786\/ca2d5\/media.mpd",
                "hlsUrl": "\/\/v.tvpage.com\/1758166\/158904786\/ca2d5\/media.m3u8",
                "uploadAsset": false,
                "quality": "",
                "cc": [
                    {
                        "label": "English",
                        "srclang": "en",
                        "src": "\/\/v.tvpage.com\/1758166\/158904786\/cc\/vtt\/en_1524158621.vtt",
                        "default": true
                    }
                ],
                "sources": [
                    {
                        "file": "\/\/v.tvpage.com\/1758166\/158904786\/ca2d5\/1080p_media.mp4",
                        "quality": "1080p",
                        "mime": "video\/mp4",
                        "width": 1280,
                        "height": 720
                    },
                    {
                        "file": "\/\/v.tvpage.com\/1758166\/158904786\/ca2d5\/720p_media.mp4",
                        "quality": "720p",
                        "mime": "video\/mp4",
                        "width": 1280,
                        "height": 720
                    },
                    {
                        "file": "\/\/v.tvpage.com\/1758166\/158904786\/ca2d5\/480p_media.mp4",
                        "quality": "480p",
                        "mime": "video\/mp4",
                        "width": 854,
                        "height": 480
                    },
                    {
                        "file": "\/\/v.tvpage.com\/1758166\/158904786\/ca2d5\/360p_media.mp4",
                        "quality": "360p",
                        "mime": "video\/mp4",
                        "width": 640,
                        "height": 360
                    },
                    {
                        "file": "\/\/v.tvpage.com\/1758166\/158904786\/ca2d5\/240p_media.mp4",
                        "quality": "240p",
                        "mime": "video\/mp4",
                        "width": 320,
                        "height": 180
                    }
                ]
            },
            "parentId": "114661406",
            "url": "\/latest-videos\/fishtail-chignon-hair-braid-tutorial-prom-hairstyles-garnier-fructis-style\/114661406-158904786"
        },
        {
            "id": "158635735",
            "title": "Bring it on with AVEENO\u00ae ULTRA-CALMING\u00ae Facial Cleanser & Moisturizer",
            "date_created": "1523405849",
            "loginId": "1758166",
            "tags": "",
            "description": "",
            "asset": {
                "user": {
                    "firstName": "",
                    "lastName": "",
                    "emailAddress": ""
                },
                "videoMeta": {
                    "duration": "15",
                    "width": 1280,
                    "height": 720
                },
                "mediaDuration": "15",
                "prettyDuration": "00:00:15",
                "thumbnailUrl": "\/\/v.tvpage.com\/1758166\/158635735\/249e7\/thumb-0a553545f658dd9315e00be498f0c113-00001.jpg",
                "type": "mp4",
                "dashUrl": "\/\/v.tvpage.com\/1758166\/158635735\/249e7\/media.mpd",
                "hlsUrl": "\/\/v.tvpage.com\/1758166\/158635735\/249e7\/media.m3u8",
                "uploadAsset": false,
                "quality": "",
                "cc": [
                    {
                        "label": "English",
                        "srclang": "en",
                        "src": "\/\/v.tvpage.com\/1758166\/158635735\/cc\/vtt\/en_1524158478.vtt",
                        "default": true
                    }
                ],
                "sources": [
                    {
                        "file": "\/\/v.tvpage.com\/1758166\/158635735\/249e7\/1080p_media.mp4",
                        "quality": "1080p",
                        "mime": "video\/mp4",
                        "width": 1280,
                        "height": 720
                    },
                    {
                        "file": "\/\/v.tvpage.com\/1758166\/158635735\/249e7\/720p_media.mp4",
                        "quality": "720p",
                        "mime": "video\/mp4",
                        "width": 1280,
                        "height": 720
                    },
                    {
                        "file": "\/\/v.tvpage.com\/1758166\/158635735\/249e7\/480p_media.mp4",
                        "quality": "480p",
                        "mime": "video\/mp4",
                        "width": 854,
                        "height": 480
                    },
                    {
                        "file": "\/\/v.tvpage.com\/1758166\/158635735\/249e7\/360p_media.mp4",
                        "quality": "360p",
                        "mime": "video\/mp4",
                        "width": 640,
                        "height": 360
                    },
                    {
                        "file": "\/\/v.tvpage.com\/1758166\/158635735\/249e7\/240p_media.mp4",
                        "quality": "240p",
                        "mime": "video\/mp4",
                        "width": 320,
                        "height": 180
                    }
                ]
            },
            "parentId": "114661406",
            "url": "\/latest-videos\/bring-it-on-with-aveeno-ultra-calming-facial-cleanser-moisturizer\/114661406-158635735"
        },
        {
            "id": "158633735",
            "title": "Green Saver Herb Keepers",
            "date_created": "1523405847",
            "loginId": "1758166",
            "tags": "",
            "description": "",
            "asset": {
                "user": {
                    "firstName": "",
                    "lastName": "",
                    "emailAddress": ""
                },
                "videoMeta": {
                    "duration": "33",
                    "width": 1280,
                    "height": 720
                },
                "mediaDuration": "33",
                "prettyDuration": "00:00:33",
                "thumbnailUrl": "\/\/sitecdn.tvpage.com\/live\/users\/1758166\/canvas\/1920\/1080\/398441955-1523406935.jpg",
                "type": "mp4",
                "uploadAsset": false,
                "quality": "",
                "cc": [
                    {
                        "label": "English",
                        "srclang": "en",
                        "src": "\/\/v.tvpage.com\/1758166\/158633735\/cc\/vtt\/en_1524158429.vtt",
                        "default": true
                    }
                ],
                "sources": [
                    {
                        "file": "\/\/v.tvpage.com\/1758166\/158633735\/f9c3b\/1080p_media.mp4",
                        "quality": "1080p",
                        "mime": "video\/mp4",
                        "width": 1280,
                        "height": 720
                    },
                    {
                        "file": "\/\/v.tvpage.com\/1758166\/158633735\/f9c3b\/720p_media.mp4",
                        "quality": "720p",
                        "mime": "video\/mp4",
                        "width": 1280,
                        "height": 720
                    },
                    {
                        "file": "\/\/v.tvpage.com\/1758166\/158633735\/f9c3b\/480p_media.mp4",
                        "quality": "480p",
                        "mime": "video\/mp4",
                        "width": 854,
                        "height": 480
                    },
                    {
                        "file": "\/\/v.tvpage.com\/1758166\/158633735\/f9c3b\/360p_media.mp4",
                        "quality": "360p",
                        "mime": "video\/mp4",
                        "width": 640,
                        "height": 360
                    },
                    {
                        "file": "\/\/v.tvpage.com\/1758166\/158633735\/f9c3b\/240p_media.mp4",
                        "quality": "240p",
                        "mime": "video\/mp4",
                        "width": 320,
                        "height": 180
                    }
                ]
            },
            "parentId": "114661406",
            "url": "\/latest-videos\/green-saver-herb-keepers\/114661406-158633735"
        },
        {
            "id": "158633734",
            "title": "PerfectPull  Wipes Dispenser",
            "date_created": "1523405844",
            "loginId": "1758166",
            "tags": "",
            "description": "",
            "asset": {
                "user": {
                    "firstName": "",
                    "lastName": "",
                    "emailAddress": ""
                },
                "videoMeta": {
                    "duration": "21",
                    "width": 1280,
                    "height": 720
                },
                "mediaDuration": "21",
                "prettyDuration": "00:00:21",
                "thumbnailUrl": "\/\/sitecdn.tvpage.com\/live\/users\/1758166\/canvas\/1920\/1080\/862893660-1523406957.jpg",
                "type": "mp4",
                "uploadAsset": false,
                "quality": "",
                "cc": [
                    {
                        "label": "English",
                        "srclang": "en",
                        "src": "\/\/v.tvpage.com\/1758166\/158633734\/cc\/vtt\/en_1524158349.vtt",
                        "default": true
                    }
                ],
                "sources": [
                    {
                        "file": "\/\/v.tvpage.com\/1758166\/158633734\/6fc5c\/1080p_media.mp4",
                        "quality": "1080p",
                        "mime": "video\/mp4",
                        "width": 1280,
                        "height": 720
                    },
                    {
                        "file": "\/\/v.tvpage.com\/1758166\/158633734\/6fc5c\/720p_media.mp4",
                        "quality": "720p",
                        "mime": "video\/mp4",
                        "width": 1280,
                        "height": 720
                    },
                    {
                        "file": "\/\/v.tvpage.com\/1758166\/158633734\/6fc5c\/480p_media.mp4",
                        "quality": "480p",
                        "mime": "video\/mp4",
                        "width": 854,
                        "height": 480
                    },
                    {
                        "file": "\/\/v.tvpage.com\/1758166\/158633734\/6fc5c\/360p_media.mp4",
                        "quality": "360p",
                        "mime": "video\/mp4",
                        "width": 640,
                        "height": 360
                    },
                    {
                        "file": "\/\/v.tvpage.com\/1758166\/158633734\/6fc5c\/240p_media.mp4",
                        "quality": "240p",
                        "mime": "video\/mp4",
                        "width": 320,
                        "height": 180
                    }
                ]
            },
            "parentId": "114661406",
            "url": "\/latest-videos\/perfectpull-wipes-dispenser\/114661406-158633734"
        },
        {
            "id": "158633732",
            "title": "GreenSaver Crisper Insert",
            "date_created": "1523405840",
            "loginId": "1758166",
            "tags": "",
            "description": "",
            "asset": {
                "user": {
                    "firstName": "",
                    "lastName": "",
                    "emailAddress": ""
                },
                "videoMeta": {
                    "duration": "28",
                    "width": 1280,
                    "height": 720
                },
                "mediaDuration": "28",
                "prettyDuration": "00:00:28",
                "thumbnailUrl": "\/\/sitecdn.tvpage.com\/live\/users\/1758166\/canvas\/1920\/1080\/429002434-1523407013.jpg",
                "type": "mp4",
                "dashUrl": "\/\/v.tvpage.com\/1758166\/158633732\/07e8a\/media.mpd",
                "hlsUrl": "\/\/v.tvpage.com\/1758166\/158633732\/07e8a\/media.m3u8",
                "uploadAsset": false,
                "quality": "",
                "cc": [
                    {
                        "label": "English",
                        "srclang": "en",
                        "src": "\/\/v.tvpage.com\/1758166\/158633732\/cc\/vtt\/en_1524158306.vtt",
                        "default": true
                    }
                ],
                "sources": [
                    {
                        "file": "\/\/v.tvpage.com\/1758166\/158633732\/07e8a\/1080p_media.mp4",
                        "quality": "1080p",
                        "mime": "video\/mp4",
                        "width": 1280,
                        "height": 720
                    },
                    {
                        "file": "\/\/v.tvpage.com\/1758166\/158633732\/07e8a\/720p_media.mp4",
                        "quality": "720p",
                        "mime": "video\/mp4",
                        "width": 1280,
                        "height": 720
                    },
                    {
                        "file": "\/\/v.tvpage.com\/1758166\/158633732\/07e8a\/480p_media.mp4",
                        "quality": "480p",
                        "mime": "video\/mp4",
                        "width": 854,
                        "height": 480
                    },
                    {
                        "file": "\/\/v.tvpage.com\/1758166\/158633732\/07e8a\/360p_media.mp4",
                        "quality": "360p",
                        "mime": "video\/mp4",
                        "width": 640,
                        "height": 360
                    },
                    {
                        "file": "\/\/v.tvpage.com\/1758166\/158633732\/07e8a\/240p_media.mp4",
                        "quality": "240p",
                        "mime": "video\/mp4",
                        "width": 320,
                        "height": 180
                    }
                ]
            },
            "parentId": "114661406",
            "url": "\/latest-videos\/greensaver-crisper-insert\/114661406-158633732"
        },
        {
            "id": "158633731",
            "title": "Stainless Steel Measuring Spoons",
            "date_created": "1523405837",
            "loginId": "1758166",
            "tags": "",
            "description": "",
            "asset": {
                "user": {
                    "firstName": "",
                    "lastName": "",
                    "emailAddress": ""
                },
                "videoMeta": {
                    "duration": "34",
                    "width": 1280,
                    "height": 720
                },
                "mediaDuration": "34",
                "prettyDuration": "00:00:34",
                "thumbnailUrl": "\/\/sitecdn.tvpage.com\/live\/users\/1758166\/canvas\/1920\/1080\/606627238-1523407042.jpg",
                "type": "mp4",
                "uploadAsset": false,
                "quality": "",
                "cc": [
                    {
                        "label": "English",
                        "srclang": "en",
                        "src": "\/\/v.tvpage.com\/1758166\/158633731\/cc\/vtt\/en_1524158227.vtt",
                        "default": true
                    }
                ],
                "sources": [
                    {
                        "file": "\/\/v.tvpage.com\/1758166\/158633731\/c9b91\/1080p_media.mp4",
                        "quality": "1080p",
                        "mime": "video\/mp4",
                        "width": 1280,
                        "height": 720
                    },
                    {
                        "file": "\/\/v.tvpage.com\/1758166\/158633731\/c9b91\/720p_media.mp4",
                        "quality": "720p",
                        "mime": "video\/mp4",
                        "width": 1280,
                        "height": 720
                    },
                    {
                        "file": "\/\/v.tvpage.com\/1758166\/158633731\/c9b91\/480p_media.mp4",
                        "quality": "480p",
                        "mime": "video\/mp4",
                        "width": 854,
                        "height": 480
                    },
                    {
                        "file": "\/\/v.tvpage.com\/1758166\/158633731\/c9b91\/360p_media.mp4",
                        "quality": "360p",
                        "mime": "video\/mp4",
                        "width": 640,
                        "height": 360
                    },
                    {
                        "file": "\/\/v.tvpage.com\/1758166\/158633731\/c9b91\/240p_media.mp4",
                        "quality": "240p",
                        "mime": "video\/mp4",
                        "width": 320,
                        "height": 180
                    }
                ]
            },
            "parentId": "114661406",
            "url": "\/latest-videos\/stainless-steel-measuring-spoons\/114661406-158633731"
        },
        {
            "id": "158633730",
            "title": "Stainless Steel Squeegee",
            "date_created": "1523405834",
            "loginId": "1758166",
            "tags": "",
            "description": "",
            "asset": {
                "user": {
                    "firstName": "",
                    "lastName": "",
                    "emailAddress": ""
                },
                "videoMeta": {
                    "duration": "25",
                    "width": 1280,
                    "height": 720
                },
                "mediaDuration": "25",
                "prettyDuration": "00:00:25",
                "thumbnailUrl": "\/\/sitecdn.tvpage.com\/live\/users\/1758166\/canvas\/1920\/1080\/655092311-1523407092.jpg",
                "type": "mp4",
                "uploadAsset": false,
                "quality": "",
                "cc": [
                    {
                        "label": "English",
                        "srclang": "en",
                        "src": "\/\/v.tvpage.com\/1758166\/158633730\/cc\/vtt\/en_1524158181.vtt",
                        "default": true
                    }
                ],
                "sources": [
                    {
                        "file": "\/\/v.tvpage.com\/1758166\/158633730\/153cb\/1080p_media.mp4",
                        "quality": "1080p",
                        "mime": "video\/mp4",
                        "width": 1280,
                        "height": 720
                    },
                    {
                        "file": "\/\/v.tvpage.com\/1758166\/158633730\/153cb\/720p_media.mp4",
                        "quality": "720p",
                        "mime": "video\/mp4",
                        "width": 1280,
                        "height": 720
                    },
                    {
                        "file": "\/\/v.tvpage.com\/1758166\/158633730\/153cb\/480p_media.mp4",
                        "quality": "480p",
                        "mime": "video\/mp4",
                        "width": 854,
                        "height": 480
                    },
                    {
                        "file": "\/\/v.tvpage.com\/1758166\/158633730\/153cb\/360p_media.mp4",
                        "quality": "360p",
                        "mime": "video\/mp4",
                        "width": 640,
                        "height": 360
                    },
                    {
                        "file": "\/\/v.tvpage.com\/1758166\/158633730\/153cb\/240p_media.mp4",
                        "quality": "240p",
                        "mime": "video\/mp4",
                        "width": 320,
                        "height": 180
                    }
                ]
            },
            "parentId": "114661406",
            "url": "\/latest-videos\/stainless-steel-squeegee\/114661406-158633730"
        },
        {
            "id": "158633729",
            "title": "All Purpose Squeegee",
            "date_created": "1523405831",
            "loginId": "1758166",
            "tags": "",
            "description": "",
            "asset": {
                "user": {
                    "firstName": "",
                    "lastName": "",
                    "emailAddress": ""
                },
                "videoMeta": {
                    "duration": "26",
                    "width": 1280,
                    "height": 720
                },
                "mediaDuration": "26",
                "prettyDuration": "00:00:26",
                "thumbnailUrl": "\/\/sitecdn.tvpage.com\/live\/users\/1758166\/canvas\/1920\/1080\/641289512-1523407117.jpg",
                "type": "mp4",
                "dashUrl": "\/\/v.tvpage.com\/1758166\/158633729\/5561e\/media.mpd",
                "hlsUrl": "\/\/v.tvpage.com\/1758166\/158633729\/5561e\/media.m3u8",
                "uploadAsset": false,
                "quality": "",
                "cc": [
                    {
                        "label": "English",
                        "srclang": "en",
                        "src": "\/\/v.tvpage.com\/1758166\/158633729\/cc\/vtt\/en_1524158121.vtt",
                        "default": true
                    }
                ],
                "sources": [
                    {
                        "file": "\/\/v.tvpage.com\/1758166\/158633729\/5561e\/1080p_media.mp4",
                        "quality": "1080p",
                        "mime": "video\/mp4",
                        "width": 1280,
                        "height": 720
                    },
                    {
                        "file": "\/\/v.tvpage.com\/1758166\/158633729\/5561e\/720p_media.mp4",
                        "quality": "720p",
                        "mime": "video\/mp4",
                        "width": 1280,
                        "height": 720
                    },
                    {
                        "file": "\/\/v.tvpage.com\/1758166\/158633729\/5561e\/480p_media.mp4",
                        "quality": "480p",
                        "mime": "video\/mp4",
                        "width": 854,
                        "height": 480
                    },
                    {
                        "file": "\/\/v.tvpage.com\/1758166\/158633729\/5561e\/360p_media.mp4",
                        "quality": "360p",
                        "mime": "video\/mp4",
                        "width": 640,
                        "height": 360
                    },
                    {
                        "file": "\/\/v.tvpage.com\/1758166\/158633729\/5561e\/240p_media.mp4",
                        "quality": "240p",
                        "mime": "video\/mp4",
                        "width": 320,
                        "height": 180
                    }
                ]
            },
            "parentId": "114661406",
            "url": "\/latest-videos\/all-purpose-squeegee\/114661406-158633729"
        },
        {
            "id": "158633728",
            "title": "Chrome Suction Series",
            "date_created": "1523405829",
            "loginId": "1758166",
            "tags": "",
            "description": "",
            "asset": {
                "user": {
                    "firstName": "",
                    "lastName": "",
                    "emailAddress": ""
                },
                "videoMeta": {
                    "duration": "29",
                    "width": 1280,
                    "height": 720
                },
                "mediaDuration": "29",
                "prettyDuration": "00:00:29",
                "thumbnailUrl": "\/\/sitecdn.tvpage.com\/live\/users\/1758166\/canvas\/1920\/1080\/856277428-1523407139.jpg",
                "type": "mp4",
                "uploadAsset": false,
                "quality": "",
                "cc": [
                    {
                        "label": "English",
                        "srclang": "en",
                        "src": "\/\/v.tvpage.com\/1758166\/158633728\/cc\/vtt\/en_1524158057.vtt",
                        "default": true
                    }
                ],
                "sources": [
                    {
                        "file": "\/\/v.tvpage.com\/1758166\/158633728\/83dcc\/1080p_media.mp4",
                        "quality": "1080p",
                        "mime": "video\/mp4",
                        "width": 1280,
                        "height": 720
                    },
                    {
                        "file": "\/\/v.tvpage.com\/1758166\/158633728\/83dcc\/720p_media.mp4",
                        "quality": "720p",
                        "mime": "video\/mp4",
                        "width": 1280,
                        "height": 720
                    },
                    {
                        "file": "\/\/v.tvpage.com\/1758166\/158633728\/83dcc\/480p_media.mp4",
                        "quality": "480p",
                        "mime": "video\/mp4",
                        "width": 854,
                        "height": 480
                    },
                    {
                        "file": "\/\/v.tvpage.com\/1758166\/158633728\/83dcc\/360p_media.mp4",
                        "quality": "360p",
                        "mime": "video\/mp4",
                        "width": 640,
                        "height": 360
                    },
                    {
                        "file": "\/\/v.tvpage.com\/1758166\/158633728\/83dcc\/240p_media.mp4",
                        "quality": "240p",
                        "mime": "video\/mp4",
                        "width": 320,
                        "height": 180
                    }
                ]
            },
            "parentId": "114661406",
            "url": "\/latest-videos\/chrome-suction-series\/114661406-158633728"
        },
        {
            "id": "158635736",
            "title": "Eczema Treatments for Mother & Daughter| Aveeno",
            "date_created": "1523405851",
            "loginId": "1758166",
            "tags": "",
            "description": "",
            "asset": {
                "user": {
                    "firstName": "",
                    "lastName": "",
                    "emailAddress": ""
                },
                "videoMeta": {
                    "duration": "30",
                    "width": 1280,
                    "height": 720
                },
                "mediaDuration": "30",
                "prettyDuration": "00:00:30",
                "thumbnailUrl": "\/\/sitecdn.tvpage.com\/live\/users\/1758166\/canvas\/1920\/1080\/926244740-1523406900.jpg",
                "type": "mp4",
                "uploadAsset": false,
                "quality": "",
                "cc": [
                    {
                        "label": "English",
                        "srclang": "en",
                        "src": "\/\/v.tvpage.com\/1758166\/158635736\/cc\/vtt\/en_1524158013.vtt",
                        "default": true
                    }
                ],
                "sources": [
                    {
                        "file": "\/\/v.tvpage.com\/1758166\/158635736\/e9c75\/1080p_media.mp4",
                        "quality": "1080p",
                        "mime": "video\/mp4",
                        "width": 1280,
                        "height": 720
                    },
                    {
                        "file": "\/\/v.tvpage.com\/1758166\/158635736\/e9c75\/720p_media.mp4",
                        "quality": "720p",
                        "mime": "video\/mp4",
                        "width": 1280,
                        "height": 720
                    },
                    {
                        "file": "\/\/v.tvpage.com\/1758166\/158635736\/e9c75\/480p_media.mp4",
                        "quality": "480p",
                        "mime": "video\/mp4",
                        "width": 854,
                        "height": 480
                    },
                    {
                        "file": "\/\/v.tvpage.com\/1758166\/158635736\/e9c75\/360p_media.mp4",
                        "quality": "360p",
                        "mime": "video\/mp4",
                        "width": 640,
                        "height": 360
                    },
                    {
                        "file": "\/\/v.tvpage.com\/1758166\/158635736\/e9c75\/240p_media.mp4",
                        "quality": "240p",
                        "mime": "video\/mp4",
                        "width": 320,
                        "height": 180
                    }
                ]
            },
            "parentId": "114661406",
            "url": "\/latest-videos\/eczema-treatments-for-mother-daughter-aveeno\/114661406-158635736"
        },
        {
            "id": "158615471",
            "title": "Deep Clean Brush Set",
            "date_created": "1523310045",
            "loginId": "1758166",
            "tags": "",
            "description": "",
            "asset": {
                "user": {
                    "firstName": "",
                    "lastName": "",
                    "emailAddress": ""
                },
                "videoMeta": {
                    "duration": "23",
                    "width": 1280,
                    "height": 720
                },
                "mediaDuration": "23",
                "prettyDuration": "00:00:23",
                "thumbnailUrl": "\/\/sitecdn.tvpage.com\/live\/users\/1758166\/canvas\/1920\/1080\/524114451-1523311656.jpg",
                "type": "mp4",
                "dashUrl": "\/\/v.tvpage.com\/1758166\/158615471\/3096e\/media.mpd",
                "hlsUrl": "\/\/v.tvpage.com\/1758166\/158615471\/3096e\/media.m3u8",
                "uploadAsset": false,
                "quality": "",
                "cc": [
                    {
                        "label": "English",
                        "srclang": "en",
                        "src": "\/\/v.tvpage.com\/1758166\/158615471\/cc\/vtt\/en_1524157777.vtt",
                        "default": true
                    }
                ],
                "sources": [
                    {
                        "file": "\/\/v.tvpage.com\/1758166\/158615471\/3096e\/1080p_media.mp4",
                        "quality": "1080p",
                        "mime": "video\/mp4",
                        "width": 1280,
                        "height": 720
                    },
                    {
                        "file": "\/\/v.tvpage.com\/1758166\/158615471\/3096e\/720p_media.mp4",
                        "quality": "720p",
                        "mime": "video\/mp4",
                        "width": 1280,
                        "height": 720
                    },
                    {
                        "file": "\/\/v.tvpage.com\/1758166\/158615471\/3096e\/480p_media.mp4",
                        "quality": "480p",
                        "mime": "video\/mp4",
                        "width": 854,
                        "height": 480
                    },
                    {
                        "file": "\/\/v.tvpage.com\/1758166\/158615471\/3096e\/360p_media.mp4",
                        "quality": "360p",
                        "mime": "video\/mp4",
                        "width": 640,
                        "height": 360
                    },
                    {
                        "file": "\/\/v.tvpage.com\/1758166\/158615471\/3096e\/240p_media.mp4",
                        "quality": "240p",
                        "mime": "video\/mp4",
                        "width": 320,
                        "height": 180
                    }
                ]
            },
            "parentId": "114661406",
            "url": "\/latest-videos\/deep-clean-brush-set\/114661406-158615471"
        },
        {
            "id": "158615470",
            "title": "FurLifter Carpet Rake",
            "date_created": "1523310043",
            "loginId": "1758166",
            "tags": "",
            "description": "",
            "asset": {
                "user": {
                    "firstName": "",
                    "lastName": "",
                    "emailAddress": ""
                },
                "videoMeta": {
                    "duration": "28",
                    "width": 1280,
                    "height": 720
                },
                "mediaDuration": "28",
                "prettyDuration": "00:00:28",
                "thumbnailUrl": "\/\/sitecdn.tvpage.com\/live\/users\/1758166\/canvas\/1920\/1080\/132860590-1523311708.jpg",
                "type": "mp4",
                "dashUrl": "\/\/v.tvpage.com\/1758166\/158615470\/5a67a\/media.mpd",
                "hlsUrl": "\/\/v.tvpage.com\/1758166\/158615470\/5a67a\/media.m3u8",
                "uploadAsset": false,
                "quality": "",
                "cc": [
                    {
                        "label": "English",
                        "srclang": "en",
                        "src": "\/\/v.tvpage.com\/1758166\/158615470\/cc\/vtt\/en_1524157726.vtt",
                        "default": true
                    }
                ],
                "sources": [
                    {
                        "file": "\/\/v.tvpage.com\/1758166\/158615470\/5a67a\/1080p_media.mp4",
                        "quality": "1080p",
                        "mime": "video\/mp4",
                        "width": 1280,
                        "height": 720
                    },
                    {
                        "file": "\/\/v.tvpage.com\/1758166\/158615470\/5a67a\/720p_media.mp4",
                        "quality": "720p",
                        "mime": "video\/mp4",
                        "width": 1280,
                        "height": 720
                    },
                    {
                        "file": "\/\/v.tvpage.com\/1758166\/158615470\/5a67a\/480p_media.mp4",
                        "quality": "480p",
                        "mime": "video\/mp4",
                        "width": 854,
                        "height": 480
                    },
                    {
                        "file": "\/\/v.tvpage.com\/1758166\/158615470\/5a67a\/360p_media.mp4",
                        "quality": "360p",
                        "mime": "video\/mp4",
                        "width": 640,
                        "height": 360
                    },
                    {
                        "file": "\/\/v.tvpage.com\/1758166\/158615470\/5a67a\/240p_media.mp4",
                        "quality": "240p",
                        "mime": "video\/mp4",
                        "width": 320,
                        "height": 180
                    }
                ]
            },
            "parentId": "114661406",
            "url": "\/latest-videos\/furlifter-carpet-rake\/114661406-158615470"
        },
        {
            "id": "158615469",
            "title": "StrongHold Suction Grip Bar",
            "date_created": "1523310041",
            "loginId": "1758166",
            "tags": "",
            "description": "",
            "asset": {
                "user": {
                    "firstName": "",
                    "lastName": "",
                    "emailAddress": ""
                },
                "videoMeta": {
                    "duration": "24",
                    "width": 1280,
                    "height": 720
                },
                "mediaDuration": "24",
                "prettyDuration": "00:00:24",
                "thumbnailUrl": "\/\/sitecdn.tvpage.com\/live\/users\/1758166\/canvas\/1920\/1080\/315250323-1523311787.jpg",
                "type": "mp4",
                "dashUrl": "\/\/v.tvpage.com\/1758166\/158615469\/26184\/media.mpd",
                "hlsUrl": "\/\/v.tvpage.com\/1758166\/158615469\/26184\/media.m3u8",
                "uploadAsset": false,
                "quality": "",
                "cc": [
                    {
                        "label": "English",
                        "srclang": "en",
                        "src": "\/\/v.tvpage.com\/1758166\/158615469\/cc\/vtt\/en_1524157632.vtt",
                        "default": true
                    }
                ],
                "sources": [
                    {
                        "file": "\/\/v.tvpage.com\/1758166\/158615469\/26184\/1080p_media.mp4",
                        "quality": "1080p",
                        "mime": "video\/mp4",
                        "width": 1280,
                        "height": 720
                    },
                    {
                        "file": "\/\/v.tvpage.com\/1758166\/158615469\/26184\/720p_media.mp4",
                        "quality": "720p",
                        "mime": "video\/mp4",
                        "width": 1280,
                        "height": 720
                    },
                    {
                        "file": "\/\/v.tvpage.com\/1758166\/158615469\/26184\/480p_media.mp4",
                        "quality": "480p",
                        "mime": "video\/mp4",
                        "width": 854,
                        "height": 480
                    },
                    {
                        "file": "\/\/v.tvpage.com\/1758166\/158615469\/26184\/360p_media.mp4",
                        "quality": "360p",
                        "mime": "video\/mp4",
                        "width": 640,
                        "height": 360
                    },
                    {
                        "file": "\/\/v.tvpage.com\/1758166\/158615469\/26184\/240p_media.mp4",
                        "quality": "240p",
                        "mime": "video\/mp4",
                        "width": 320,
                        "height": 180
                    }
                ]
            },
            "parentId": "114661406",
            "url": "\/latest-videos\/stronghold-suction-grip-bar\/114661406-158615469"
        },
        {
            "id": "158615468",
            "title": "StrongHold Suction Grip Bar - Brushed Nickel",
            "date_created": "1523310039",
            "loginId": "1758166",
            "tags": "",
            "description": "",
            "asset": {
                "user": {
                    "firstName": "",
                    "lastName": "",
                    "emailAddress": ""
                },
                "videoMeta": {
                    "duration": "26",
                    "width": 1280,
                    "height": 720
                },
                "mediaDuration": "26",
                "prettyDuration": "00:00:26",
                "thumbnailUrl": "\/\/sitecdn.tvpage.com\/live\/users\/1758166\/canvas\/1920\/1080\/996602915-1523311837.jpg",
                "type": "mp4",
                "dashUrl": "\/\/v.tvpage.com\/1758166\/158615468\/31f0e\/media.mpd",
                "hlsUrl": "\/\/v.tvpage.com\/1758166\/158615468\/31f0e\/media.m3u8",
                "uploadAsset": false,
                "quality": "",
                "cc": [
                    {
                        "label": "English",
                        "srclang": "en",
                        "src": "\/\/v.tvpage.com\/1758166\/158615468\/cc\/vtt\/en_1524157529.vtt",
                        "default": true
                    }
                ],
                "sources": [
                    {
                        "file": "\/\/v.tvpage.com\/1758166\/158615468\/31f0e\/1080p_media.mp4",
                        "quality": "1080p",
                        "mime": "video\/mp4",
                        "width": 1280,
                        "height": 720
                    },
                    {
                        "file": "\/\/v.tvpage.com\/1758166\/158615468\/31f0e\/720p_media.mp4",
                        "quality": "720p",
                        "mime": "video\/mp4",
                        "width": 1280,
                        "height": 720
                    },
                    {
                        "file": "\/\/v.tvpage.com\/1758166\/158615468\/31f0e\/480p_media.mp4",
                        "quality": "480p",
                        "mime": "video\/mp4",
                        "width": 854,
                        "height": 480
                    },
                    {
                        "file": "\/\/v.tvpage.com\/1758166\/158615468\/31f0e\/360p_media.mp4",
                        "quality": "360p",
                        "mime": "video\/mp4",
                        "width": 640,
                        "height": 360
                    },
                    {
                        "file": "\/\/v.tvpage.com\/1758166\/158615468\/31f0e\/240p_media.mp4",
                        "quality": "240p",
                        "mime": "video\/mp4",
                        "width": 320,
                        "height": 180
                    }
                ]
            },
            "parentId": "114661406",
            "url": "\/latest-videos\/stronghold-suction-grip-bar-brushed-nickel\/114661406-158615468"
        }
    ]
}