{
    "title": "Dished: 5 Waffle Maker Recipe Hacks",
    "description": "",
    "referenceId": "3bf6e02a9bca551c0d1427ee0c3b345d",
    "date_created": "1524698923",
    "date_modified": "1525192313",
    "tags": "",
    "sourceId": "6",
    "VIDEO_LENGTH": "SHORT",
    "video_type": null,
    "status": "approved",
    "visibility": "1",
    "category_id_1": null,
    "category_id_2": null,
    "category_id_3": null,
    "category_id_4": null,
    "category_id_5": null,
    "Concept": null,
    "mod_request": null,
    "cc_request": "done1",
    "creator": null,
    "video_classification1": null,
    "user_id": "0",
    "id": "162282824",
    "loginId": "1758166",
    "entityType": "1",
    "titleTextEncoded": "Dished-5-Waffle-Maker-Recipe-Hacks",
    "category": "",
    "duration": "67",
    "settings": "",
    "asset": {
        "user": {
            "firstName": "",
            "lastName": "",
            "emailAddress": ""
        },
        "videoMeta": {
            "duration": "67",
            "width": 1280,
            "height": 720
        },
        "mediaDuration": "67",
        "prettyDuration": "00:01:07",
        "thumbnailUrl": "\/\/v.tvpage.com\/1758166\/162282824\/b205c\/thumb-3bf6e02a9bca551c0d1427ee0c3b345d-00002.jpg",
        "type": "mp4",
        "uploadAsset": false,
        "quality": "",
        "cc": [
            {
                "label": "English",
                "srclang": "en",
                "src": "\/\/v.tvpage.com\/1758166\/162282824\/cc\/vtt\/en_1525192299.vtt",
                "default": true
            }
        ],
        "sources": [
            {
                "file": "\/\/v.tvpage.com\/1758166\/162282824\/b205c\/1080p_media.mp4",
                "quality": "1080p",
                "mime": "video\/mp4",
                "width": 1280,
                "height": 720
            },
            {
                "file": "\/\/v.tvpage.com\/1758166\/162282824\/b205c\/720p_media.mp4",
                "quality": "720p",
                "mime": "video\/mp4",
                "width": 1280,
                "height": 720
            },
            {
                "file": "\/\/v.tvpage.com\/1758166\/162282824\/b205c\/480p_media.mp4",
                "quality": "480p",
                "mime": "video\/mp4",
                "width": 854,
                "height": 480
            },
            {
                "file": "\/\/v.tvpage.com\/1758166\/162282824\/b205c\/360p_media.mp4",
                "quality": "360p",
                "mime": "video\/mp4",
                "width": 640,
                "height": 360
            },
            {
                "file": "\/\/v.tvpage.com\/1758166\/162282824\/b205c\/240p_media.mp4",
                "quality": "240p",
                "mime": "video\/mp4",
                "width": 320,
                "height": 180
            }
        ]
    },
    "transcripts": "",
    "VV_VI": "",
    "CVV_VI": "",
    "engagement_score": "",
    "conversion_score": "",
    "metrics_statistics": "",
    "delete": "",
    "notes": "",
    "uploader": "",
    "modified_date": "",
    "created_date": "",
    "tvp_profiles": [],
    "tvp_profiles_manual": "",
    "tvp_profiles_maxscore": "",
    "tvp_profiles_nlp": "",
    "tvp_profiles_account": "",
    "tvp_profiles_manual_account": "",
    "tvp_profiles_maxscore_account": "",
    "tvp_enhanced_search": null,
    "tvp_enhanced_anti": null,
    "tvp_enhanced_brand": null,
    "tvp_enhanced_video_images": null,
    "tvp_enhanced_transcript": null
}