{
    "title": "Learn more about the Breville Smart Fryer\u2122",
    "description": "Learn more about the Smart Fryer\u2122",
    "referenceId": "jDwjkLeDjV8",
    "date_created": "1456174864",
    "date_modified": "1468528599",
    "tags": "",
    "sourceId": "4",
    "VIDEO_LENGTH": "SHORT",
    "video_type": null,
    "status": "approved",
    "visibility": "1",
    "category_id_1": null,
    "category_id_2": null,
    "category_id_3": null,
    "category_id_4": null,
    "category_id_5": null,
    "Concept": null,
    "mod_request": null,
    "cc_request": null,
    "creator": null,
    "video_classification1": null,
    "user_id": "0",
    "id": "66784848",
    "loginId": "1758166",
    "entityType": "1",
    "titleTextEncoded": "Learn-more-about-the-Breville-Smart-Fryer",
    "category": "",
    "duration": 89,
    "settings": "",
    "asset": {
        "type": "youtube",
        "thumbnailUrl": "https:\/\/i.ytimg.com\/vi\/jDwjkLeDjV8\/hqdefault.jpg",
        "uploadDate": 1456174864,
        "videoId": "jDwjkLeDjV8",
        "title": "Learn more about the Breville Smart Fryer\u2122",
        "description": "Learn more about the Smart Fryer\u2122\nhttp:\/\/www.brevilleusa.com\/smart-fryer-bdf500xl.html\n\nLearn more about Breville:\nhttp:\/\/www.brevilleusa.com\n\nSubscribe to our YouTube Channel:\nhttp:\/\/www.youtube.com\/subscription_center?add_user=breville\n\nLike us on Facebook:\nhttps:\/\/www.facebook.com\/brevilleusa\/\n\nPin us on Pinterest:\nhttp:\/\/pinterest.com\/brevilleusa\/\n\nFollow us on Twitter:\nhttps:\/\/twitter.com\/brevilleusa\/\n\nSee us on Instagram:\nhttps:\/\/www.instagram.com\/breville\/\n\nBreville has a recipe site check it out!\nhttp:\/\/foodthinkers.com\/",
        "author": "breville",
        "mediaDuration": 89,
        "prettyDuration": "00:01:29",
        "views": "743517",
        "uploadAsset": false,
        "quality": ""
    },
    "transcripts": "[MUSIC PLAYING]\n\nIntroducing the Breville Smart Fryer. The first deep fryer that adjusts time and temperature to suit what you're cooking. Let's see it in action.  From fries to fish and wings to donuts, this versatile fryer ensures your food is always crisp. The Smart Fryer, brought to you by the food thinkers of Breville",
    "VV_VI": 139,
    "CVV_VI": null,
    "engagement_score": 0,
    "conversion_score": null,
    "metrics_statistics": "{\"VV_VI\":{\"engagement_score\":{\"lastUpdatedDate\":\"2018-05-31\"}}}",
    "delete": null,
    "notes": null,
    "uploader": null,
    "modified_date": null,
    "created_date": null,
    "tvp_profiles": [
        "14",
        "12",
        "11"
    ],
    "tvp_profiles_manual": null,
    "tvp_profiles_maxscore": 7495.997,
    "tvp_profiles_nlp": null,
    "tvp_profiles_account": null,
    "tvp_profiles_manual_account": null,
    "tvp_profiles_maxscore_account": null,
    "tvp_enhanced_search": null,
    "tvp_enhanced_anti": null,
    "tvp_enhanced_brand": null,
    "tvp_enhanced_video_images": null,
    "tvp_enhanced_transcript": null
}